Workbook
Name 類別清單: '選單設定'!$A$2:$A$50
Name 付款方式清單: '選單設定'!$B$2:$B$50
Name 薪資計入清單: '選單設定'!$E$2:$E$4
Name 收支類型清單: '選單設定'!$C$2:$C$3
Name 是否清單: '選單設定'!$D$2:$D$3

Sheet 月度總覽
A1: 月計記帳本｜動態每日配額
A2: 先輸入黃色欄位 → 登記固定支出與日常收支 → 查看動態配額與每日順向結果
A4: ① 週期與資金設定 | E4: ② 即時計算結果
A5: 週期開始日 | B5: 46231 | C5: 自訂計算週期的第一天 | E5: 週期天數 | F5: =IF(OR(B5="",B6="",B6<B5),0,B6-B5+1) -> 11
A6: 週期結束日 | B6: 46241 | C6: 自訂計算週期的最後一天 | E6: 配額起算日 | F6: =IF(F5=0,"",MAX(B5,MIN(B7,B6))) -> 2026-07-28
A7: 配額計算基準日 | B7: =TODAY() -> 2026-07-28 | C7: 預設今天；可覆寫為任何日期做情境試算 | E7: 剩餘天數（含基準日） | F7: =IF(F5=0,0,MAX(0,B6-F6+1)) -> 11
A8: 自訂發薪日 | B8: 46241 | C8: 輸入完整日期 | E8: 已計入薪資 | F8: =IF(AND(B8>=B5,B8<=B6),IF(B10="全期預先計入",B9,IF(B10="到帳日自動計入",IF(B8<=B7,B9,0),0)),0) -> #VALUE!
A9: 薪資金額 | B9: 22500 | C9: 請勿在收支明細重複登記同一筆薪資 | E9: 其他收入（截至基準日） | F9: =SUMIFS('收支明細'!$E:$E,'收支明細'!$B:$B,"收入",'收支明細'!$A:$A,">="&B5,'收支明細'!$A:$A,"<="&MIN(B7,B6)) -> #VALUE!
A10: 薪資計入方式 | B10: 到帳日自動計入 | C10: 到帳日計入／全期計入／不計入 | E10: 實際支出（截至基準日） | F10: =SUMIFS('收支明細'!$E:$E,'收支明細'!$B:$B,"支出",'收支明細'!$A:$A,">="&B5,'收支明細'!$A:$A,"<="&MIN(B7,B6)) -> #VALUE!
A11: 期初可用餘額 | B11: 10000 | C11: 週期開始時可動用的餘額 | E11: 未付固定支出預留 | F11: =SUMIFS('固定支出'!$C:$C,'固定支出'!$G:$G,"是",'固定支出'!$F:$F,"否",'固定支出'!$D:$D,">="&B5,'固定支出'!$D:$D,"<="&B6) -> #VALUE!
E12: 剩餘可變動資金 | F12: =B11+F8+F9-F10-F11 -> #VALUE!
E13: 動態每天平均配額 | F13: =IF(F7=0,0,MAX(0,F12/F7)) -> #VALUE!
A14: ③ 順向結果摘要
A15: 若由配額起算日起每天花足配額，週期末可變動資金 | E15: =F12-(F13*F7) -> #VALUE!
A16: 尚未到帳且可能在本週期加入的薪資 | E16: =IF(AND(B10="到帳日自動計入",B8>B7,B8<=B6),B9,0) -> #VALUE!
A17: 計入未來薪資後的週期末預測餘額 | E17: =B15+B16 -> #VALUE!
A20: 提示：固定支出尚未付款時會先預留；付款後請在「收支明細」登記支出，並在「固定支出」把已付款改為『是』，避免重複扣減。

Sheet 收支明細
A1: 收支明細｜只填一行一筆
A3: 日期 | B3: 類型 | C3: 類別 | D3: 項目／說明 | E3: 金額 | F3: 付款方式 | G3: 備註

Sheet 固定支出
A1: 固定支出｜設定扣款日期並追蹤付款
A3: 固定支出名稱 | B3: 類別 | C3: 金額 | D3: 本期扣款日期 | E3: 付款方式 | F3: 已付款 | G3: 啟用 | H3: 備註

Sheet 每日順向結果
A1: 每日順向結果｜由自訂起始日至結束日
A2: 藍欄為事件／實績；紫欄為依目前動態配額推演的未來可變動資金（固定支出已在總覽先行預留）。
A4: 日期 | B4: 星期 | C4: 狀態 | D4: 薪資事件 | E4: 其他收入 | F4: 固定支出到期 | G4: 實際支出 | H4: 建議可變支出 | I4: 當日實際淨額 | J4: 順向可變資金
A5: =IF(1<='月度總覽'!$F$5,'月度總覽'!$B$5+1-1,"") -> 2026-07-28 | B5: =IF(A5="","",TEXT(A5,"aaa")) -> aaa | C5: =IF(A5="","",IF(A5<'月度總覽'!$F$6,"已過",IF(A5='月度總覽'!$F$6,"基準日","未來"))) -> 基準日 | D5: =IF(A5="","",IF(A5='月度總覽'!$B$8,'月度總覽'!$B$9,0)) -> 0.00 | E5: =IF(A5="","",SUMIFS('收支明細'!$E:$E,'收支明細'!$B:$B,"收入",'收支明細'!$A:$A,A5)) -> 0.00 | F5: =IF(A5="","",SUMIFS('固定支出'!$C:$C,'固定支出'!$G:$G,"是",'固定支出'!$D:$D,A5)) -> 0.00 | G5: =IF(A5="","",SUMIFS('收支明細'!$E:$E,'收支明細'!$B:$B,"支出",'收支明細'!$A:$A,A5)) -> 0.00 | H5: =IF(OR(A5="",A5<'月度總覽'!$F$6),0,'月度總覽'!$F$13) -> 909.09 | I5: =IF(A5="","",D5+E5-G5) -> 0.00 | J5: =IF(OR(A5="",A5<'月度總覽'!$F$6),"",'月度總覽'!$F$12-SUM($H$5:H5)+IF(AND('月度總覽'!$B$10="到帳日自動計入",'月度總覽'!$B$8>'月度總覽'!$B$7,'月度總覽'!$B$8<=A5),'月度總覽'!$B$9,0)+SUMIFS($E$5:E5,$A$5:A5,">"&'月度總覽'!$B$7)-SUMIFS($G$5:G5,$A$5:A5,">"&'月度總覽'!$B$7)) -> 9,090.91
A6: =IF(2<='月度總覽'!$F$5,'月度總覽'!$B$5+2-1,"") -> 2026-07-29 | B6: =IF(A6="","",TEXT(A6,"aaa")) -> aaa | C6: =IF(A6="","",IF(A6<'月度總覽'!$F$6,"已過",IF(A6='月度總覽'!$F$6,"基準日","未來"))) -> 未來 | D6: =IF(A6="","",IF(A6='月度總覽'!$B$8,'月度總覽'!$B$9,0)) -> 0.00 | E6: =IF(A6="","",SUMIFS('收支明細'!$E:$E,'收支明細'!$B:$B,"收入",'收支明細'!$A:$A,A6)) -> 0.00 | F6: =IF(A6="","",SUMIFS('固定支出'!$C:$C,'固定支出'!$G:$G,"是",'固定支出'!$D:$D,A6)) -> 0.00 | G6: =IF(A6="","",SUMIFS('收支明細'!$E:$E,'收支明細'!$B:$B,"支出",'收支明細'!$A:$A,A6)) -> 0.00 | H6: =IF(OR(A6="",A6<'月度總覽'!$F$6),0,'月度總覽'!$F$13) -> 909.09 | I6: =IF(A6="","",D6+E6-G6) -> 0.00 | J6: =IF(OR(A6="",A6<'月度總覽'!$F$6),"",'月度總覽'!$F$12-SUM($H$5:H6)+IF(AND('月度總覽'!$B$10="到帳日自動計入",'月度總覽'!$B$8>'月度總覽'!$B$7,'月度總覽'!$B$8<=A6),'月度總覽'!$B$9,0)+SUMIFS($E$5:E6,$A$5:A6,">"&'月度總覽'!$B$7)-SUMIFS($G$5:G6,$A$5:A6,">"&'月度總覽'!$B$7)) -> 8,181.82
A7: =IF(3<='月度總覽'!$F$5,'月度總覽'!$B$5+3-1,"") -> 2026-07-30 | B7: =IF(A7="","",TEXT(A7,"aaa")) -> aaa | C7: =IF(A7="","",IF(A7<'月度總覽'!$F$6,"已過",IF(A7='月度總覽'!$F$6,"基準日","未來"))) -> 未來 | D7: =IF(A7="","",IF(A7='月度總覽'!$B$8,'月度總覽'!$B$9,0)) -> 0.00 | E7: =IF(A7="","",SUMIFS('收支明細'!$E:$E,'收支明細'!$B:$B,"收入",'收支明細'!$A:$A,A7)) -> 0.00 | F7: =IF(A7="","",SUMIFS('固定支出'!$C:$C,'固定支出'!$G:$G,"是",'固定支出'!$D:$D,A7)) -> 0.00 | G7: =IF(A7="","",SUMIFS('收支明細'!$E:$E,'收支明細'!$B:$B,"支出",'收支明細'!$A:$A,A7)) -> 0.00 | H7: =IF(OR(A7="",A7<'月度總覽'!$F$6),0,'月度總覽'!$F$13) -> 909.09 | I7: =IF(A7="","",D7+E7-G7) -> 0.00 | J7: =IF(OR(A7="",A7<'月度總覽'!$F$6),"",'月度總覽'!$F$12-SUM($H$5:H7)+IF(AND('月度總覽'!$B$10="到帳日自動計入",'月度總覽'!$B$8>'月度總覽'!$B$7,'月度總覽'!$B$8<=A7),'月度總覽'!$B$9,0)+SUMIFS($E$5:E7,$A$5:A7,">"&'月度總覽'!$B$7)-SUMIFS($G$5:G7,$A$5:A7,">"&'月度總覽'!$B$7)) -> 7,272.73
A8: =IF(4<='月度總覽'!$F$5,'月度總覽'!$B$5+4-1,"") -> 2026-07-31 | B8: =IF(A8="","",TEXT(A8,"aaa")) -> aaa | C8: =IF(A8="","",IF(A8<'月度總覽'!$F$6,"已過",IF(A8='月度總覽'!$F$6,"基準日","未來"))) -> 未來 | D8: =IF(A8="","",IF(A8='月度總覽'!$B$8,'月度總覽'!$B$9,0)) -> 0.00 | E8: =IF(A8="","",SUMIFS('收支明細'!$E:$E,'收支明細'!$B:$B,"收入",'收支明細'!$A:$A,A8)) -> 0.00 | F8: =IF(A8="","",SUMIFS('固定支出'!$C:$C,'固定支出'!$G:$G,"是",'固定支出'!$D:$D,A8)) -> 0.00 | G8: =IF(A8="","",SUMIFS('收支明細'!$E:$E,'收支明細'!$B:$B,"支出",'收支明細'!$A:$A,A8)) -> 0.00 | H8: =IF(OR(A8="",A8<'月度總覽'!$F$6),0,'月度總覽'!$F$13) -> 909.09 | I8: =IF(A8="","",D8+E8-G8) -> 0.00 | J8: =IF(OR(A8="",A8<'月度總覽'!$F$6),"",'月度總覽'!$F$12-SUM($H$5:H8)+IF(AND('月度總覽'!$B$10="到帳日自動計入",'月度總覽'!$B$8>'月度總覽'!$B$7,'月度總覽'!$B$8<=A8),'月度總覽'!$B$9,0)+SUMIFS($E$5:E8,$A$5:A8,">"&'月度總覽'!$B$7)-SUMIFS($G$5:G8,$A$5:A8,">"&'月度總覽'!$B$7)) -> 6,363.64
A9: =IF(5<='月度總覽'!$F$5,'月度總覽'!$B$5+5-1,"") -> 2026-08-01 | B9: =IF(A9="","",TEXT(A9,"aaa")) -> aaa | C9: =IF(A9="","",IF(A9<'月度總覽'!$F$6,"已過",IF(A9='月度總覽'!$F$6,"基準日","未來"))) -> 未來 | D9: =IF(A9="","",IF(A9='月度總覽'!$B$8,'月度總覽'!$B$9,0)) -> 0.00 | E9: =IF(A9="","",SUMIFS('收支明細'!$E:$E,'收支明細'!$B:$B,"收入",'收支明細'!$A:$A,A9)) -> 0.00 | F9: =IF(A9="","",SUMIFS('固定支出'!$C:$C,'固定支出'!$G:$G,"是",'固定支出'!$D:$D,A9)) -> 0.00 | G9: =IF(A9="","",SUMIFS('收支明細'!$E:$E,'收支明細'!$B:$B,"支出",'收支明細'!$A:$A,A9)) -> 0.00 | H9: =IF(OR(A9="",A9<'月度總覽'!$F$6),0,'月度總覽'!$F$13) -> 909.09 | I9: =IF(A9="","",D9+E9-G9) -> 0.00 | J9: =IF(OR(A9="",A9<'月度總覽'!$F$6),"",'月度總覽'!$F$12-SUM($H$5:H9)+IF(AND('月度總覽'!$B$10="到帳日自動計入",'月度總覽'!$B$8>'月度總覽'!$B$7,'月度總覽'!$B$8<=A9),'月度總覽'!$B$9,0)+SUMIFS($E$5:E9,$A$5:A9,">"&'月度總覽'!$B$7)-SUMIFS($G$5:G9,$A$5:A9,">"&'月度總覽'!$B$7)) -> 5,454.55
A10: =IF(6<='月度總覽'!$F$5,'月度總覽'!$B$5+6-1,"") -> 2026-08-02 | B10: =IF(A10="","",TEXT(A10,"aaa")) -> aaa | C10: =IF(A10="","",IF(A10<'月度總覽'!$F$6,"已過",IF(A10='月度總覽'!$F$6,"基準日","未來"))) -> 未來 | D10: =IF(A10="","",IF(A10='月度總覽'!$B$8,'月度總覽'!$B$9,0)) -> 0.00 | E10: =IF(A10="","",SUMIFS('收支明細'!$E:$E,'收支明細'!$B:$B,"收入",'收支明細'!$A:$A,A10)) -> 0.00 | F10: =IF(A10="","",SUMIFS('固定支出'!$C:$C,'固定支出'!$G:$G,"是",'固定支出'!$D:$D,A10)) -> 0.00 | G10: =IF(A10="","",SUMIFS('收支明細'!$E:$E,'收支明細'!$B:$B,"支出",'收支明細'!$A:$A,A10)) -> 0.00 | H10: =IF(OR(A10="",A10<'月度總覽'!$F$6),0,'月度總覽'!$F$13) -> 909.09 | I10: =IF(A10="","",D10+E10-G10) -> 0.00 | J10: =IF(OR(A10="",A10<'月度總覽'!$F$6),"",'月度總覽'!$F$12-SUM($H$5:H10)+IF(AND('月度總覽'!$B$10="到帳日自動計入",'月度總覽'!$B$8>'月度總覽'!$B$7,'月度總覽'!$B$8<=A10),'月度總覽'!$B$9,0)+SUMIFS($E$5:E10,$A$5:A10,">"&'月度總覽'!$B$7)-SUMIFS($G$5:G10,$A$5:A10,">"&'月度總覽'!$B$7)) -> 4,545.45
A11: =IF(7<='月度總覽'!$F$5,'月度總覽'!$B$5+7-1,"") -> 2026-08-03 | B11: =IF(A11="","",TEXT(A11,"aaa")) -> aaa | C11: =IF(A11="","",IF(A11<'月度總覽'!$F$6,"已過",IF(A11='月度總覽'!$F$6,"基準日","未來"))) -> 未來 | D11: =IF(A11="","",IF(A11='月度總覽'!$B$8,'月度總覽'!$B$9,0)) -> 0.00 | E11: =IF(A11="","",SUMIFS('收支明細'!$E:$E,'收支明細'!$B:$B,"收入",'收支明細'!$A:$A,A11)) -> 0.00 | F11: =IF(A11="","",SUMIFS('固定支出'!$C:$C,'固定支出'!$G:$G,"是",'固定支出'!$D:$D,A11)) -> 0.00 | G11: =IF(A11="","",SUMIFS('收支明細'!$E:$E,'收支明細'!$B:$B,"支出",'收支明細'!$A:$A,A11)) -> 0.00 | H11: =IF(OR(A11="",A11<'月度總覽'!$F$6),0,'月度總覽'!$F$13) -> 909.09 | I11: =IF(A11="","",D11+E11-G11) -> 0.00 | J11: =IF(OR(A11="",A11<'月度總覽'!$F$6),"",'月度總覽'!$F$12-SUM($H$5:H11)+IF(AND('月度總覽'!$B$10="到帳日自動計入",'月度總覽'!$B$8>'月度總覽'!$B$7,'月度總覽'!$B$8<=A11),'月度總覽'!$B$9,0)+SUMIFS($E$5:E11,$A$5:A11,">"&'月度總覽'!$B$7)-SUMIFS($G$5:G11,$A$5:A11,">"&'月度總覽'!$B$7)) -> 3,636.36
A12: =IF(8<='月度總覽'!$F$5,'月度總覽'!$B$5+8-1,"") -> 2026-08-04 | B12: =IF(A12="","",TEXT(A12,"aaa")) -> aaa | C12: =IF(A12="","",IF(A12<'月度總覽'!$F$6,"已過",IF(A12='月度總覽'!$F$6,"基準日","未來"))) -> 未來 | D12: =IF(A12="","",IF(A12='月度總覽'!$B$8,'月度總覽'!$B$9,0)) -> 0.00 | E12: =IF(A12="","",SUMIFS('收支明細'!$E:$E,'收支明細'!$B:$B,"收入",'收支明細'!$A:$A,A12)) -> 0.00 | F12: =IF(A12="","",SUMIFS('固定支出'!$C:$C,'固定支出'!$G:$G,"是",'固定支出'!$D:$D,A12)) -> 0.00 | G12: =IF(A12="","",SUMIFS('收支明細'!$E:$E,'收支明細'!$B:$B,"支出",'收支明細'!$A:$A,A12)) -> 0.00 | H12: =IF(OR(A12="",A12<'月度總覽'!$F$6),0,'月度總覽'!$F$13) -> 909.09 | I12: =IF(A12="","",D12+E12-G12) -> 0.00 | J12: =IF(OR(A12="",A12<'月度總覽'!$F$6),"",'月度總覽'!$F$12-SUM($H$5:H12)+IF(AND('月度總覽'!$B$10="到帳日自動計入",'月度總覽'!$B$8>'月度總覽'!$B$7,'月度總覽'!$B$8<=A12),'月度總覽'!$B$9,0)+SUMIFS($E$5:E12,$A$5:A12,">"&'月度總覽'!$B$7)-SUMIFS($G$5:G12,$A$5:A12,">"&'月度總覽'!$B$7)) -> 2,727.27
A13: =IF(9<='月度總覽'!$F$5,'月度總覽'!$B$5+9-1,"") -> 2026-08-05 | B13: =IF(A13="","",TEXT(A13,"aaa")) -> aaa | C13: =IF(A13="","",IF(A13<'月度總覽'!$F$6,"已過",IF(A13='月度總覽'!$F$6,"基準日","未來"))) -> 未來 | D13: =IF(A13="","",IF(A13='月度總覽'!$B$8,'月度總覽'!$B$9,0)) -> 0.00 | E13: =IF(A13="","",SUMIFS('收支明細'!$E:$E,'收支明細'!$B:$B,"收入",'收支明細'!$A:$A,A13)) -> 0.00 | F13: =IF(A13="","",SUMIFS('固定支出'!$C:$C,'固定支出'!$G:$G,"是",'固定支出'!$D:$D,A13)) -> 0.00 | G13: =IF(A13="","",SUMIFS('收支明細'!$E:$E,'收支明細'!$B:$B,"支出",'收支明細'!$A:$A,A13)) -> 0.00 | H13: =IF(OR(A13="",A13<'月度總覽'!$F$6),0,'月度總覽'!$F$13) -> 909.09 | I13: =IF(A13="","",D13+E13-G13) -> 0.00 | J13: =IF(OR(A13="",A13<'月度總覽'!$F$6),"",'月度總覽'!$F$12-SUM($H$5:H13)+IF(AND('月度總覽'!$B$10="到帳日自動計入",'月度總覽'!$B$8>'月度總覽'!$B$7,'月度總覽'!$B$8<=A13),'月度總覽'!$B$9,0)+SUMIFS($E$5:E13,$A$5:A13,">"&'月度總覽'!$B$7)-SUMIFS($G$5:G13,$A$5:A13,">"&'月度總覽'!$B$7)) -> 1,818.18
A14: =IF(10<='月度總覽'!$F$5,'月度總覽'!$B$5+10-1,"") -> 2026-08-06 | B14: =IF(A14="","",TEXT(A14,"aaa")) -> aaa | C14: =IF(A14="","",IF(A14<'月度總覽'!$F$6,"已過",IF(A14='月度總覽'!$F$6,"基準日","未來"))) -> 未來 | D14: =IF(A14="","",IF(A14='月度總覽'!$B$8,'月度總覽'!$B$9,0)) -> 0.00 | E14: =IF(A14="","",SUMIFS('收支明細'!$E:$E,'收支明細'!$B:$B,"收入",'收支明細'!$A:$A,A14)) -> 0.00 | F14: =IF(A14="","",SUMIFS('固定支出'!$C:$C,'固定支出'!$G:$G,"是",'固定支出'!$D:$D,A14)) -> 0.00 | G14: =IF(A14="","",SUMIFS('收支明細'!$E:$E,'收支明細'!$B:$B,"支出",'收支明細'!$A:$A,A14)) -> 0.00 | H14: =IF(OR(A14="",A14<'月度總覽'!$F$6),0,'月度總覽'!$F$13) -> 909.09 | I14: =IF(A14="","",D14+E14-G14) -> 0.00 | J14: =IF(OR(A14="",A14<'月度總覽'!$F$6),"",'月度總覽'!$F$12-SUM($H$5:H14)+IF(AND('月度總覽'!$B$10="到帳日自動計入",'月度總覽'!$B$8>'月度總覽'!$B$7,'月度總覽'!$B$8<=A14),'月度總覽'!$B$9,0)+SUMIFS($E$5:E14,$A$5:A14,">"&'月度總覽'!$B$7)-SUMIFS($G$5:G14,$A$5:A14,">"&'月度總覽'!$B$7)) -> 909.09
A15: =IF(11<='月度總覽'!$F$5,'月度總覽'!$B$5+11-1,"") -> 2026-08-07 | B15: =IF(A15="","",TEXT(A15,"aaa")) -> aaa | C15: =IF(A15="","",IF(A15<'月度總覽'!$F$6,"已過",IF(A15='月度總覽'!$F$6,"基準日","未來"))) -> 未來 | D15: =IF(A15="","",IF(A15='月度總覽'!$B$8,'月度總覽'!$B$9,0)) -> 22,500.00 | E15: =IF(A15="","",SUMIFS('收支明細'!$E:$E,'收支明細'!$B:$B,"收入",'收支明細'!$A:$A,A15)) -> 0.00 | F15: =IF(A15="","",SUMIFS('固定支出'!$C:$C,'固定支出'!$G:$G,"是",'固定支出'!$D:$D,A15)) -> 0.00 | G15: =IF(A15="","",SUMIFS('收支明細'!$E:$E,'收支明細'!$B:$B,"支出",'收支明細'!$A:$A,A15)) -> 0.00 | H15: =IF(OR(A15="",A15<'月度總覽'!$F$6),0,'月度總覽'!$F$13) -> 909.09 | I15: =IF(A15="","",D15+E15-G15) -> 22,500.00 | J15: =IF(OR(A15="",A15<'月度總覽'!$F$6),"",'月度總覽'!$F$12-SUM($H$5:H15)+IF(AND('月度總覽'!$B$10="到帳日自動計入",'月度總覽'!$B$8>'月度總覽'!$B$7,'月度總覽'!$B$8<=A15),'月度總覽'!$B$9,0)+SUMIFS($E$5:E15,$A$5:A15,">"&'月度總覽'!$B$7)-SUMIFS($G$5:G15,$A$5:A15,">"&'月度總覽'!$B$7)) -> 22,500.00
A16: =IF(12<='月度總覽'!$F$5,'月度總覽'!$B$5+12-1,"") | B16: =IF(A16="","",TEXT(A16,"aaa")) | C16: =IF(A16="","",IF(A16<'月度總覽'!$F$6,"已過",IF(A16='月度總覽'!$F$6,"基準日","未來"))) | D16: =IF(A16="","",IF(A16='月度總覽'!$B$8,'月度總覽'!$B$9,0)) | E16: =IF(A16="","",SUMIFS('收支明細'!$E:$E,'收支明細'!$B:$B,"收入",'收支明細'!$A:$A,A16)) | F16: =IF(A16="","",SUMIFS('固定支出'!$C:$C,'固定支出'!$G:$G,"是",'固定支出'!$D:$D,A16)) | G16: =IF(A16="","",SUMIFS('收支明細'!$E:$E,'收支明細'!$B:$B,"支出",'收支明細'!$A:$A,A16)) | H16: =IF(OR(A16="",A16<'月度總覽'!$F$6),0,'月度總覽'!$F$13) -> 0.00 | I16: =IF(A16="","",D16+E16-G16) | J16: =IF(OR(A16="",A16<'月度總覽'!$F$6),"",'月度總覽'!$F$12-SUM($H$5:H16)+IF(AND('月度總覽'!$B$10="到帳日自動計入",'月度總覽'!$B$8>'月度總覽'!$B$7,'月度總覽'!$B$8<=A16),'月度總覽'!$B$9,0)+SUMIFS($E$5:E16,$A$5:A16,">"&'月度總覽'!$B$7)-SUMIFS($G$5:G16,$A$5:A16,">"&'月度總覽'!$B$7))
A17: =IF(13<='月度總覽'!$F$5,'月度總覽'!$B$5+13-1,"") | B17: =IF(A17="","",TEXT(A17,"aaa")) | C17: =IF(A17="","",IF(A17<'月度總覽'!$F$6,"已過",IF(A17='月度總覽'!$F$6,"基準日","未來"))) | D17: =IF(A17="","",IF(A17='月度總覽'!$B$8,'月度總覽'!$B$9,0)) | E17: =IF(A17="","",SUMIFS('收支明細'!$E:$E,'收支明細'!$B:$B,"收入",'收支明細'!$A:$A,A17)) | F17: =IF(A17="","",SUMIFS('固定支出'!$C:$C,'固定支出'!$G:$G,"是",'固定支出'!$D:$D,A17)) | G17: =IF(A17="","",SUMIFS('收支明細'!$E:$E,'收支明細'!$B:$B,"支出",'收支明細'!$A:$A,A17)) | H17: =IF(OR(A17="",A17<'月度總覽'!$F$6),0,'月度總覽'!$F$13) -> 0.00 | I17: =IF(A17="","",D17+E17-G17) | J17: =IF(OR(A17="",A17<'月度總覽'!$F$6),"",'月度總覽'!$F$12-SUM($H$5:H17)+IF(AND('月度總覽'!$B$10="到帳日自動計入",'月度總覽'!$B$8>'月度總覽'!$B$7,'月度總覽'!$B$8<=A17),'月度總覽'!$B$9,0)+SUMIFS($E$5:E17,$A$5:A17,">"&'月度總覽'!$B$7)-SUMIFS($G$5:G17,$A$5:A17,">"&'月度總覽'!$B$7))
A18: =IF(14<='月度總覽'!$F$5,'月度總覽'!$B$5+14-1,"") | B18: =IF(A18="","",TEXT(A18,"aaa")) | C18: =IF(A18="","",IF(A18<'月度總覽'!$F$6,"已過",IF(A18='月度總覽'!$F$6,"基準日","未來"))) | D18: =IF(A18="","",IF(A18='月度總覽'!$B$8,'月度總覽'!$B$9,0)) | E18: =IF(A18="","",SUMIFS('收支明細'!$E:$E,'收支明細'!$B:$B,"收入",'收支明細'!$A:$A,A18)) | F18: =IF(A18="","",SUMIFS('固定支出'!$C:$C,'固定支出'!$G:$G,"是",'固定支出'!$D:$D,A18)) | G18: =IF(A18="","",SUMIFS('收支明細'!$E:$E,'收支明細'!$B:$B,"支出",'收支明細'!$A:$A,A18)) | H18: =IF(OR(A18="",A18<'月度總覽'!$F$6),0,'月度總覽'!$F$13) -> 0.00 | I18: =IF(A18="","",D18+E18-G18) | J18: =IF(OR(A18="",A18<'月度總覽'!$F$6),"",'月度總覽'!$F$12-SUM($H$5:H18)+IF(AND('月度總覽'!$B$10="到帳日自動計入",'月度總覽'!$B$8>'月度總覽'!$B$7,'月度總覽'!$B$8<=A18),'月度總覽'!$B$9,0)+SUMIFS($E$5:E18,$A$5:A18,">"&'月度總覽'!$B$7)-SUMIFS($G$5:G18,$A$5:A18,">"&'月度總覽'!$B$7))
A19: =IF(15<='月度總覽'!$F$5,'月度總覽'!$B$5+15-1,"") | B19: =IF(A19="","",TEXT(A19,"aaa")) | C19: =IF(A19="","",IF(A19<'月度總覽'!$F$6,"已過",IF(A19='月度總覽'!$F$6,"基準日","未來"))) | D19: =IF(A19="","",IF(A19='月度總覽'!$B$8,'月度總覽'!$B$9,0)) | E19: =IF(A19="","",SUMIFS('收支明細'!$E:$E,'收支明細'!$B:$B,"收入",'收支明細'!$A:$A,A19)) | F19: =IF(A19="","",SUMIFS('固定支出'!$C:$C,'固定支出'!$G:$G,"是",'固定支出'!$D:$D,A19)) | G19: =IF(A19="","",SUMIFS('收支明細'!$E:$E,'收支明細'!$B:$B,"支出",'收支明細'!$A:$A,A19)) | H19: =IF(OR(A19="",A19<'月度總覽'!$F$6),0,'月度總覽'!$F$13) -> 0.00 | I19: =IF(A19="","",D19+E19-G19) | J19: =IF(OR(A19="",A19<'月度總覽'!$F$6),"",'月度總覽'!$F$12-SUM($H$5:H19)+IF(AND('月度總覽'!$B$10="到帳日自動計入",'月度總覽'!$B$8>'月度總覽'!$B$7,'月度總覽'!$B$8<=A19),'月度總覽'!$B$9,0)+SUMIFS($E$5:E19,$A$5:A19,">"&'月度總覽'!$B$7)-SUMIFS($G$5:G19,$A$5:A19,">"&'月度總覽'!$B$7))
A20: =IF(16<='月度總覽'!$F$5,'月度總覽'!$B$5+16-1,"") | B20: =IF(A20="","",TEXT(A20,"aaa")) | C20: =IF(A20="","",IF(A20<'月度總覽'!$F$6,"已過",IF(A20='月度總覽'!$F$6,"基準日","未來"))) | D20: =IF(A20="","",IF(A20='月度總覽'!$B$8,'月度總覽'!$B$9,0)) | E20: =IF(A20="","",SUMIFS('收支明細'!$E:$E,'收支明細'!$B:$B,"收入",'收支明細'!$A:$A,A20)) | F20: =IF(A20="","",SUMIFS('固定支出'!$C:$C,'固定支出'!$G:$G,"是",'固定支出'!$D:$D,A20)) | G20: =IF(A20="","",SUMIFS('收支明細'!$E:$E,'收支明細'!$B:$B,"支出",'收支明細'!$A:$A,A20)) | H20: =IF(OR(A20="",A20<'月度總覽'!$F$6),0,'月度總覽'!$F$13) -> 0.00 | I20: =IF(A20="","",D20+E20-G20) | J20: =IF(OR(A20="",A20<'月度總覽'!$F$6),"",'月度總覽'!$F$12-SUM($H$5:H20)+IF(AND('月度總覽'!$B$10="到帳日自動計入",'月度總覽'!$B$8>'月度總覽'!$B$7,'月度總覽'!$B$8<=A20),'月度總覽'!$B$9,0)+SUMIFS($E$5:E20,$A$5:A20,">"&'月度總覽'!$B$7)-SUMIFS($G$5:G20,$A$5:A20,">"&'月度總覽'!$B$7))
A21: =IF(17<='月度總覽'!$F$5,'月度總覽'!$B$5+17-1,"") | B21: =IF(A21="","",TEXT(A21,"aaa")) | C21: =IF(A21="","",IF(A21<'月度總覽'!$F$6,"已過",IF(A21='月度總覽'!$F$6,"基準日","未來"))) | D21: =IF(A21="","",IF(A21='月度總覽'!$B$8,'月度總覽'!$B$9,0)) | E21: =IF(A21="","",SUMIFS('收支明細'!$E:$E,'收支明細'!$B:$B,"收入",'收支明細'!$A:$A,A21)) | F21: =IF(A21="","",SUMIFS('固定支出'!$C:$C,'固定支出'!$G:$G,"是",'固定支出'!$D:$D,A21)) | G21: =IF(A21="","",SUMIFS('收支明細'!$E:$E,'收支明細'!$B:$B,"支出",'收支明細'!$A:$A,A21)) | H21: =IF(OR(A21="",A21<'月度總覽'!$F$6),0,'月度總覽'!$F$13) -> 0.00 | I21: =IF(A21="","",D21+E21-G21) | J21: =IF(OR(A21="",A21<'月度總覽'!$F$6),"",'月度總覽'!$F$12-SUM($H$5:H21)+IF(AND('月度總覽'!$B$10="到帳日自動計入",'月度總覽'!$B$8>'月度總覽'!$B$7,'月度總覽'!$B$8<=A21),'月度總覽'!$B$9,0)+SUMIFS($E$5:E21,$A$5:A21,">"&'月度總覽'!$B$7)-SUMIFS($G$5:G21,$A$5:A21,">"&'月度總覽'!$B$7))
A22: =IF(18<='月度總覽'!$F$5,'月度總覽'!$B$5+18-1,"") | B22: =IF(A22="","",TEXT(A22,"aaa")) | C22: =IF(A22="","",IF(A22<'月度總覽'!$F$6,"已過",IF(A22='月度總覽'!$F$6,"基準日","未來"))) | D22: =IF(A22="","",IF(A22='月度總覽'!$B$8,'月度總覽'!$B$9,0)) | E22: =IF(A22="","",SUMIFS('收支明細'!$E:$E,'收支明細'!$B:$B,"收入",'收支明細'!$A:$A,A22)) | F22: =IF(A22="","",SUMIFS('固定支出'!$C:$C,'固定支出'!$G:$G,"是",'固定支出'!$D:$D,A22)) | G22: =IF(A22="","",SUMIFS('收支明細'!$E:$E,'收支明細'!$B:$B,"支出",'收支明細'!$A:$A,A22)) | H22: =IF(OR(A22="",A22<'月度總覽'!$F$6),0,'月度總覽'!$F$13) -> 0.00 | I22: =IF(A22="","",D22+E22-G22) | J22: =IF(OR(A22="",A22<'月度總覽'!$F$6),"",'月度總覽'!$F$12-SUM($H$5:H22)+IF(AND('月度總覽'!$B$10="到帳日自動計入",'月度總覽'!$B$8>'月度總覽'!$B$7,'月度總覽'!$B$8<=A22),'月度總覽'!$B$9,0)+SUMIFS($E$5:E22,$A$5:A22,">"&'月度總覽'!$B$7)-SUMIFS($G$5:G22,$A$5:A22,">"&'月度總覽'!$B$7))
A23: =IF(19<='月度總覽'!$F$5,'月度總覽'!$B$5+19-1,"") | B23: =IF(A23="","",TEXT(A23,"aaa")) | C23: =IF(A23="","",IF(A23<'月度總覽'!$F$6,"已過",IF(A23='月度總覽'!$F$6,"基準日","未來"))) | D23: =IF(A23="","",IF(A23='月度總覽'!$B$8,'月度總覽'!$B$9,0)) | E23: =IF(A23="","",SUMIFS('收支明細'!$E:$E,'收支明細'!$B:$B,"收入",'收支明細'!$A:$A,A23)) | F23: =IF(A23="","",SUMIFS('固定支出'!$C:$C,'固定支出'!$G:$G,"是",'固定支出'!$D:$D,A23)) | G23: =IF(A23="","",SUMIFS('收支明細'!$E:$E,'收支明細'!$B:$B,"支出",'收支明細'!$A:$A,A23)) | H23: =IF(OR(A23="",A23<'月度總覽'!$F$6),0,'月度總覽'!$F$13) -> 0.00 | I23: =IF(A23="","",D23+E23-G23) | J23: =IF(OR(A23="",A23<'月度總覽'!$F$6),"",'月度總覽'!$F$12-SUM($H$5:H23)+IF(AND('月度總覽'!$B$10="到帳日自動計入",'月度總覽'!$B$8>'月度總覽'!$B$7,'月度總覽'!$B$8<=A23),'月度總覽'!$B$9,0)+SUMIFS($E$5:E23,$A$5:A23,">"&'月度總覽'!$B$7)-SUMIFS($G$5:G23,$A$5:A23,">"&'月度總覽'!$B$7))
A24: =IF(20<='月度總覽'!$F$5,'月度總覽'!$B$5+20-1,"") | B24: =IF(A24="","",TEXT(A24,"aaa")) | C24: =IF(A24="","",IF(A24<'月度總覽'!$F$6,"已過",IF(A24='月度總覽'!$F$6,"基準日","未來"))) | D24: =IF(A24="","",IF(A24='月度總覽'!$B$8,'月度總覽'!$B$9,0)) | E24: =IF(A24="","",SUMIFS('收支明細'!$E:$E,'收支明細'!$B:$B,"收入",'收支明細'!$A:$A,A24)) | F24: =IF(A24="","",SUMIFS('固定支出'!$C:$C,'固定支出'!$G:$G,"是",'固定支出'!$D:$D,A24)) | G24: =IF(A24="","",SUMIFS('收支明細'!$E:$E,'收支明細'!$B:$B,"支出",'收支明細'!$A:$A,A24)) | H24: =IF(OR(A24="",A24<'月度總覽'!$F$6),0,'月度總覽'!$F$13) -> 0.00 | I24: =IF(A24="","",D24+E24-G24) | J24: =IF(OR(A24="",A24<'月度總覽'!$F$6),"",'月度總覽'!$F$12-SUM($H$5:H24)+IF(AND('月度總覽'!$B$10="到帳日自動計入",'月度總覽'!$B$8>'月度總覽'!$B$7,'月度總覽'!$B$8<=A24),'月度總覽'!$B$9,0)+SUMIFS($E$5:E24,$A$5:A24,">"&'月度總覽'!$B$7)-SUMIFS($G$5:G24,$A$5:A24,">"&'月度總覽'!$B$7))
A25: =IF(21<='月度總覽'!$F$5,'月度總覽'!$B$5+21-1,"") | B25: =IF(A25="","",TEXT(A25,"aaa")) | C25: =IF(A25="","",IF(A25<'月度總覽'!$F$6,"已過",IF(A25='月度總覽'!$F$6,"基準日","未來"))) | D25: =IF(A25="","",IF(A25='月度總覽'!$B$8,'月度總覽'!$B$9,0)) | E25: =IF(A25="","",SUMIFS('收支明細'!$E:$E,'收支明細'!$B:$B,"收入",'收支明細'!$A:$A,A25)) | F25: =IF(A25="","",SUMIFS('固定支出'!$C:$C,'固定支出'!$G:$G,"是",'固定支出'!$D:$D,A25)) | G25: =IF(A25="","",SUMIFS('收支明細'!$E:$E,'收支明細'!$B:$B,"支出",'收支明細'!$A:$A,A25)) | H25: =IF(OR(A25="",A25<'月度總覽'!$F$6),0,'月度總覽'!$F$13) -> 0.00 | I25: =IF(A25="","",D25+E25-G25) | J25: =IF(OR(A25="",A25<'月度總覽'!$F$6),"",'月度總覽'!$F$12-SUM($H$5:H25)+IF(AND('月度總覽'!$B$10="到帳日自動計入",'月度總覽'!$B$8>'月度總覽'!$B$7,'月度總覽'!$B$8<=A25),'月度總覽'!$B$9,0)+SUMIFS($E$5:E25,$A$5:A25,">"&'月度總覽'!$B$7)-SUMIFS($G$5:G25,$A$5:A25,">"&'月度總覽'!$B$7))
A26: =IF(22<='月度總覽'!$F$5,'月度總覽'!$B$5+22-1,"") | B26: =IF(A26="","",TEXT(A26,"aaa")) | C26: =IF(A26="","",IF(A26<'月度總覽'!$F$6,"已過",IF(A26='月度總覽'!$F$6,"基準日","未來"))) | D26: =IF(A26="","",IF(A26='月度總覽'!$B$8,'月度總覽'!$B$9,0)) | E26: =IF(A26="","",SUMIFS('收支明細'!$E:$E,'收支明細'!$B:$B,"收入",'收支明細'!$A:$A,A26)) | F26: =IF(A26="","",SUMIFS('固定支出'!$C:$C,'固定支出'!$G:$G,"是",'固定支出'!$D:$D,A26)) | G26: =IF(A26="","",SUMIFS('收支明細'!$E:$E,'收支明細'!$B:$B,"支出",'收支明細'!$A:$A,A26)) | H26: =IF(OR(A26="",A26<'月度總覽'!$F$6),0,'月度總覽'!$F$13) -> 0.00 | I26: =IF(A26="","",D26+E26-G26) | J26: =IF(OR(A26="",A26<'月度總覽'!$F$6),"",'月度總覽'!$F$12-SUM($H$5:H26)+IF(AND('月度總覽'!$B$10="到帳日自動計入",'月度總覽'!$B$8>'月度總覽'!$B$7,'月度總覽'!$B$8<=A26),'月度總覽'!$B$9,0)+SUMIFS($E$5:E26,$A$5:A26,">"&'月度總覽'!$B$7)-SUMIFS($G$5:G26,$A$5:A26,">"&'月度總覽'!$B$7))
A27: =IF(23<='月度總覽'!$F$5,'月度總覽'!$B$5+23-1,"") | B27: =IF(A27="","",TEXT(A27,"aaa")) | C27: =IF(A27="","",IF(A27<'月度總覽'!$F$6,"已過",IF(A27='月度總覽'!$F$6,"基準日","未來"))) | D27: =IF(A27="","",IF(A27='月度總覽'!$B$8,'月度總覽'!$B$9,0)) | E27: =IF(A27="","",SUMIFS('收支明細'!$E:$E,'收支明細'!$B:$B,"收入",'收支明細'!$A:$A,A27)) | F27: =IF(A27="","",SUMIFS('固定支出'!$C:$C,'固定支出'!$G:$G,"是",'固定支出'!$D:$D,A27)) | G27: =IF(A27="","",SUMIFS('收支明細'!$E:$E,'收支明細'!$B:$B,"支出",'收支明細'!$A:$A,A27)) | H27: =IF(OR(A27="",A27<'月度總覽'!$F$6),0,'月度總覽'!$F$13) -> 0.00 | I27: =IF(A27="","",D27+E27-G27) | J27: =IF(OR(A27="",A27<'月度總覽'!$F$6),"",'月度總覽'!$F$12-SUM($H$5:H27)+IF(AND('月度總覽'!$B$10="到帳日自動計入",'月度總覽'!$B$8>'月度總覽'!$B$7,'月度總覽'!$B$8<=A27),'月度總覽'!$B$9,0)+SUMIFS($E$5:E27,$A$5:A27,">"&'月度總覽'!$B$7)-SUMIFS($G$5:G27,$A$5:A27,">"&'月度總覽'!$B$7))
A28: =IF(24<='月度總覽'!$F$5,'月度總覽'!$B$5+24-1,"") | B28: =IF(A28="","",TEXT(A28,"aaa")) | C28: =IF(A28="","",IF(A28<'月度總覽'!$F$6,"已過",IF(A28='月度總覽'!$F$6,"基準日","未來"))) | D28: =IF(A28="","",IF(A28='月度總覽'!$B$8,'月度總覽'!$B$9,0)) | E28: =IF(A28="","",SUMIFS('收支明細'!$E:$E,'收支明細'!$B:$B,"收入",'收支明細'!$A:$A,A28)) | F28: =IF(A28="","",SUMIFS('固定支出'!$C:$C,'固定支出'!$G:$G,"是",'固定支出'!$D:$D,A28)) | G28: =IF(A28="","",SUMIFS('收支明細'!$E:$E,'收支明細'!$B:$B,"支出",'收支明細'!$A:$A,A28)) | H28: =IF(OR(A28="",A28<'月度總覽'!$F$6),0,'月度總覽'!$F$13) -> 0.00 | I28: =IF(A28="","",D28+E28-G28) | J28: =IF(OR(A28="",A28<'月度總覽'!$F$6),"",'月度總覽'!$F$12-SUM($H$5:H28)+IF(AND('月度總覽'!$B$10="到帳日自動計入",'月度總覽'!$B$8>'月度總覽'!$B$7,'月度總覽'!$B$8<=A28),'月度總覽'!$B$9,0)+SUMIFS($E$5:E28,$A$5:A28,">"&'月度總覽'!$B$7)-SUMIFS($G$5:G28,$A$5:A28,">"&'月度總覽'!$B$7))
A29: =IF(25<='月度總覽'!$F$5,'月度總覽'!$B$5+25-1,"") | B29: =IF(A29="","",TEXT(A29,"aaa")) | C29: =IF(A29="","",IF(A29<'月度總覽'!$F$6,"已過",IF(A29='月度總覽'!$F$6,"基準日","未來"))) | D29: =IF(A29="","",IF(A29='月度總覽'!$B$8,'月度總覽'!$B$9,0)) | E29: =IF(A29="","",SUMIFS('收支明細'!$E:$E,'收支明細'!$B:$B,"收入",'收支明細'!$A:$A,A29)) | F29: =IF(A29="","",SUMIFS('固定支出'!$C:$C,'固定支出'!$G:$G,"是",'固定支出'!$D:$D,A29)) | G29: =IF(A29="","",SUMIFS('收支明細'!$E:$E,'收支明細'!$B:$B,"支出",'收支明細'!$A:$A,A29)) | H29: =IF(OR(A29="",A29<'月度總覽'!$F$6),0,'月度總覽'!$F$13) -> 0.00 | I29: =IF(A29="","",D29+E29-G29) | J29: =IF(OR(A29="",A29<'月度總覽'!$F$6),"",'月度總覽'!$F$12-SUM($H$5:H29)+IF(AND('月度總覽'!$B$10="到帳日自動計入",'月度總覽'!$B$8>'月度總覽'!$B$7,'月度總覽'!$B$8<=A29),'月度總覽'!$B$9,0)+SUMIFS($E$5:E29,$A$5:A29,">"&'月度總覽'!$B$7)-SUMIFS($G$5:G29,$A$5:A29,">"&'月度總覽'!$B$7))
A30: =IF(26<='月度總覽'!$F$5,'月度總覽'!$B$5+26-1,"") | B30: =IF(A30="","",TEXT(A30,"aaa")) | C30: =IF(A30="","",IF(A30<'月度總覽'!$F$6,"已過",IF(A30='月度總覽'!$F$6,"基準日","未來"))) | D30: =IF(A30="","",IF(A30='月度總覽'!$B$8,'月度總覽'!$B$9,0)) | E30: =IF(A30="","",SUMIFS('收支明細'!$E:$E,'收支明細'!$B:$B,"收入",'收支明細'!$A:$A,A30)) | F30: =IF(A30="","",SUMIFS('固定支出'!$C:$C,'固定支出'!$G:$G,"是",'固定支出'!$D:$D,A30)) | G30: =IF(A30="","",SUMIFS('收支明細'!$E:$E,'收支明細'!$B:$B,"支出",'收支明細'!$A:$A,A30)) | H30: =IF(OR(A30="",A30<'月度總覽'!$F$6),0,'月度總覽'!$F$13) -> 0.00 | I30: =IF(A30="","",D30+E30-G30) | J30: =IF(OR(A30="",A30<'月度總覽'!$F$6),"",'月度總覽'!$F$12-SUM($H$5:H30)+IF(AND('月度總覽'!$B$10="到帳日自動計入",'月度總覽'!$B$8>'月度總覽'!$B$7,'月度總覽'!$B$8<=A30),'月度總覽'!$B$9,0)+SUMIFS($E$5:E30,$A$5:A30,">"&'月度總覽'!$B$7)-SUMIFS($G$5:G30,$A$5:A30,">"&'月度總覽'!$B$7))
A31: =IF(27<='月度總覽'!$F$5,'月度總覽'!$B$5+27-1,"") | B31: =IF(A31="","",TEXT(A31,"aaa")) | C31: =IF(A31="","",IF(A31<'月度總覽'!$F$6,"已過",IF(A31='月度總覽'!$F$6,"基準日","未來"))) | D31: =IF(A31="","",IF(A31='月度總覽'!$B$8,'月度總覽'!$B$9,0)) | E31: =IF(A31="","",SUMIFS('收支明細'!$E:$E,'收支明細'!$B:$B,"收入",'收支明細'!$A:$A,A31)) | F31: =IF(A31="","",SUMIFS('固定支出'!$C:$C,'固定支出'!$G:$G,"是",'固定支出'!$D:$D,A31)) | G31: =IF(A31="","",SUMIFS('收支明細'!$E:$E,'收支明細'!$B:$B,"支出",'收支明細'!$A:$A,A31)) | H31: =IF(OR(A31="",A31<'月度總覽'!$F$6),0,'月度總覽'!$F$13) -> 0.00 | I31: =IF(A31="","",D31+E31-G31) | J31: =IF(OR(A31="",A31<'月度總覽'!$F$6),"",'月度總覽'!$F$12-SUM($H$5:H31)+IF(AND('月度總覽'!$B$10="到帳日自動計入",'月度總覽'!$B$8>'月度總覽'!$B$7,'月度總覽'!$B$8<=A31),'月度總覽'!$B$9,0)+SUMIFS($E$5:E31,$A$5:A31,">"&'月度總覽'!$B$7)-SUMIFS($G$5:G31,$A$5:A31,">"&'月度總覽'!$B$7))
A32: =IF(28<='月度總覽'!$F$5,'月度總覽'!$B$5+28-1,"") | B32: =IF(A32="","",TEXT(A32,"aaa")) | C32: =IF(A32="","",IF(A32<'月度總覽'!$F$6,"已過",IF(A32='月度總覽'!$F$6,"基準日","未來"))) | D32: =IF(A32="","",IF(A32='月度總覽'!$B$8,'月度總覽'!$B$9,0)) | E32: =IF(A32="","",SUMIFS('收支明細'!$E:$E,'收支明細'!$B:$B,"收入",'收支明細'!$A:$A,A32)) | F32: =IF(A32="","",SUMIFS('固定支出'!$C:$C,'固定支出'!$G:$G,"是",'固定支出'!$D:$D,A32)) | G32: =IF(A32="","",SUMIFS('收支明細'!$E:$E,'收支明細'!$B:$B,"支出",'收支明細'!$A:$A,A32)) | H32: =IF(OR(A32="",A32<'月度總覽'!$F$6),0,'月度總覽'!$F$13) -> 0.00 | I32: =IF(A32="","",D32+E32-G32) | J32: =IF(OR(A32="",A32<'月度總覽'!$F$6),"",'月度總覽'!$F$12-SUM($H$5:H32)+IF(AND('月度總覽'!$B$10="到帳日自動計入",'月度總覽'!$B$8>'月度總覽'!$B$7,'月度總覽'!$B$8<=A32),'月度總覽'!$B$9,0)+SUMIFS($E$5:E32,$A$5:A32,">"&'月度總覽'!$B$7)-SUMIFS($G$5:G32,$A$5:A32,">"&'月度總覽'!$B$7))
A33: =IF(29<='月度總覽'!$F$5,'月度總覽'!$B$5+29-1,"") | B33: =IF(A33="","",TEXT(A33,"aaa")) | C33: =IF(A33="","",IF(A33<'月度總覽'!$F$6,"已過",IF(A33='月度總覽'!$F$6,"基準日","未來"))) | D33: =IF(A33="","",IF(A33='月度總覽'!$B$8,'月度總覽'!$B$9,0)) | E33: =IF(A33="","",SUMIFS('收支明細'!$E:$E,'收支明細'!$B:$B,"收入",'收支明細'!$A:$A,A33)) | F33: =IF(A33="","",SUMIFS('固定支出'!$C:$C,'固定支出'!$G:$G,"是",'固定支出'!$D:$D,A33)) | G33: =IF(A33="","",SUMIFS('收支明細'!$E:$E,'收支明細'!$B:$B,"支出",'收支明細'!$A:$A,A33)) | H33: =IF(OR(A33="",A33<'月度總覽'!$F$6),0,'月度總覽'!$F$13) -> 0.00 | I33: =IF(A33="","",D33+E33-G33) | J33: =IF(OR(A33="",A33<'月度總覽'!$F$6),"",'月度總覽'!$F$12-SUM($H$5:H33)+IF(AND('月度總覽'!$B$10="到帳日自動計入",'月度總覽'!$B$8>'月度總覽'!$B$7,'月度總覽'!$B$8<=A33),'月度總覽'!$B$9,0)+SUMIFS($E$5:E33,$A$5:A33,">"&'月度總覽'!$B$7)-SUMIFS($G$5:G33,$A$5:A33,">"&'月度總覽'!$B$7))
A34: =IF(30<='月度總覽'!$F$5,'月度總覽'!$B$5+30-1,"") | B34: =IF(A34="","",TEXT(A34,"aaa")) | C34: =IF(A34="","",IF(A34<'月度總覽'!$F$6,"已過",IF(A34='月度總覽'!$F$6,"基準日","未來"))) | D34: =IF(A34="","",IF(A34='月度總覽'!$B$8,'月度總覽'!$B$9,0)) | E34: =IF(A34="","",SUMIFS('收支明細'!$E:$E,'收支明細'!$B:$B,"收入",'收支明細'!$A:$A,A34)) | F34: =IF(A34="","",SUMIFS('固定支出'!$C:$C,'固定支出'!$G:$G,"是",'固定支出'!$D:$D,A34)) | G34: =IF(A34="","",SUMIFS('收支明細'!$E:$E,'收支明細'!$B:$B,"支出",'收支明細'!$A:$A,A34)) | H34: =IF(OR(A34="",A34<'月度總覽'!$F$6),0,'月度總覽'!$F$13) -> 0.00 | I34: =IF(A34="","",D34+E34-G34) | J34: =IF(OR(A34="",A34<'月度總覽'!$F$6),"",'月度總覽'!$F$12-SUM($H$5:H34)+IF(AND('月度總覽'!$B$10="到帳日自動計入",'月度總覽'!$B$8>'月度總覽'!$B$7,'月度總覽'!$B$8<=A34),'月度總覽'!$B$9,0)+SUMIFS($E$5:E34,$A$5:A34,">"&'月度總覽'!$B$7)-SUMIFS($G$5:G34,$A$5:A34,">"&'月度總覽'!$B$7))
A35: =IF(31<='月度總覽'!$F$5,'月度總覽'!$B$5+31-1,"") | B35: =IF(A35="","",TEXT(A35,"aaa")) | C35: =IF(A35="","",IF(A35<'月度總覽'!$F$6,"已過",IF(A35='月度總覽'!$F$6,"基準日","未來"))) | D35: =IF(A35="","",IF(A35='月度總覽'!$B$8,'月度總覽'!$B$9,0)) | E35: =IF(A35="","",SUMIFS('收支明細'!$E:$E,'收支明細'!$B:$B,"收入",'收支明細'!$A:$A,A35)) | F35: =IF(A35="","",SUMIFS('固定支出'!$C:$C,'固定支出'!$G:$G,"是",'固定支出'!$D:$D,A35)) | G35: =IF(A35="","",SUMIFS('收支明細'!$E:$E,'收支明細'!$B:$B,"支出",'收支明細'!$A:$A,A35)) | H35: =IF(OR(A35="",A35<'月度總覽'!$F$6),0,'月度總覽'!$F$13) -> 0.00 | I35: =IF(A35="","",D35+E35-G35) | J35: =IF(OR(A35="",A35<'月度總覽'!$F$6),"",'月度總覽'!$F$12-SUM($H$5:H35)+IF(AND('月度總覽'!$B$10="到帳日自動計入",'月度總覽'!$B$8>'月度總覽'!$B$7,'月度總覽'!$B$8<=A35),'月度總覽'!$B$9,0)+SUMIFS($E$5:E35,$A$5:A35,">"&'月度總覽'!$B$7)-SUMIFS($G$5:G35,$A$5:A35,">"&'月度總覽'!$B$7))
A36: =IF(32<='月度總覽'!$F$5,'月度總覽'!$B$5+32-1,"") | B36: =IF(A36="","",TEXT(A36,"aaa")) | C36: =IF(A36="","",IF(A36<'月度總覽'!$F$6,"已過",IF(A36='月度總覽'!$F$6,"基準日","未來"))) | D36: =IF(A36="","",IF(A36='月度總覽'!$B$8,'月度總覽'!$B$9,0)) | E36: =IF(A36="","",SUMIFS('收支明細'!$E:$E,'收支明細'!$B:$B,"收入",'收支明細'!$A:$A,A36)) | F36: =IF(A36="","",SUMIFS('固定支出'!$C:$C,'固定支出'!$G:$G,"是",'固定支出'!$D:$D,A36)) | G36: =IF(A36="","",SUMIFS('收支明細'!$E:$E,'收支明細'!$B:$B,"支出",'收支明細'!$A:$A,A36)) | H36: =IF(OR(A36="",A36<'月度總覽'!$F$6),0,'月度總覽'!$F$13) -> 0.00 | I36: =IF(A36="","",D36+E36-G36) | J36: =IF(OR(A36="",A36<'月度總覽'!$F$6),"",'月度總覽'!$F$12-SUM($H$5:H36)+IF(AND('月度總覽'!$B$10="到帳日自動計入",'月度總覽'!$B$8>'月度總覽'!$B$7,'月度總覽'!$B$8<=A36),'月度總覽'!$B$9,0)+SUMIFS($E$5:E36,$A$5:A36,">"&'月度總覽'!$B$7)-SUMIFS($G$5:G36,$A$5:A36,">"&'月度總覽'!$B$7))
A37: =IF(33<='月度總覽'!$F$5,'月度總覽'!$B$5+33-1,"") | B37: =IF(A37="","",TEXT(A37,"aaa")) | C37: =IF(A37="","",IF(A37<'月度總覽'!$F$6,"已過",IF(A37='月度總覽'!$F$6,"基準日","未來"))) | D37: =IF(A37="","",IF(A37='月度總覽'!$B$8,'月度總覽'!$B$9,0)) | E37: =IF(A37="","",SUMIFS('收支明細'!$E:$E,'收支明細'!$B:$B,"收入",'收支明細'!$A:$A,A37)) | F37: =IF(A37="","",SUMIFS('固定支出'!$C:$C,'固定支出'!$G:$G,"是",'固定支出'!$D:$D,A37)) | G37: =IF(A37="","",SUMIFS('收支明細'!$E:$E,'收支明細'!$B:$B,"支出",'收支明細'!$A:$A,A37)) | H37: =IF(OR(A37="",A37<'月度總覽'!$F$6),0,'月度總覽'!$F$13) -> 0.00 | I37: =IF(A37="","",D37+E37-G37) | J37: =IF(OR(A37="",A37<'月度總覽'!$F$6),"",'月度總覽'!$F$12-SUM($H$5:H37)+IF(AND('月度總覽'!$B$10="到帳日自動計入",'月度總覽'!$B$8>'月度總覽'!$B$7,'月度總覽'!$B$8<=A37),'月度總覽'!$B$9,0)+SUMIFS($E$5:E37,$A$5:A37,">"&'月度總覽'!$B$7)-SUMIFS($G$5:G37,$A$5:A37,">"&'月度總覽'!$B$7))
A38: =IF(34<='月度總覽'!$F$5,'月度總覽'!$B$5+34-1,"") | B38: =IF(A38="","",TEXT(A38,"aaa")) | C38: =IF(A38="","",IF(A38<'月度總覽'!$F$6,"已過",IF(A38='月度總覽'!$F$6,"基準日","未來"))) | D38: =IF(A38="","",IF(A38='月度總覽'!$B$8,'月度總覽'!$B$9,0)) | E38: =IF(A38="","",SUMIFS('收支明細'!$E:$E,'收支明細'!$B:$B,"收入",'收支明細'!$A:$A,A38)) | F38: =IF(A38="","",SUMIFS('固定支出'!$C:$C,'固定支出'!$G:$G,"是",'固定支出'!$D:$D,A38)) | G38: =IF(A38="","",SUMIFS('收支明細'!$E:$E,'收支明細'!$B:$B,"支出",'收支明細'!$A:$A,A38)) | H38: =IF(OR(A38="",A38<'月度總覽'!$F$6),0,'月度總覽'!$F$13) -> 0.00 | I38: =IF(A38="","",D38+E38-G38) | J38: =IF(OR(A38="",A38<'月度總覽'!$F$6),"",'月度總覽'!$F$12-SUM($H$5:H38)+IF(AND('月度總覽'!$B$10="到帳日自動計入",'月度總覽'!$B$8>'月度總覽'!$B$7,'月度總覽'!$B$8<=A38),'月度總覽'!$B$9,0)+SUMIFS($E$5:E38,$A$5:A38,">"&'月度總覽'!$B$7)-SUMIFS($G$5:G38,$A$5:A38,">"&'月度總覽'!$B$7))
A39: =IF(35<='月度總覽'!$F$5,'月度總覽'!$B$5+35-1,"") | B39: =IF(A39="","",TEXT(A39,"aaa")) | C39: =IF(A39="","",IF(A39<'月度總覽'!$F$6,"已過",IF(A39='月度總覽'!$F$6,"基準日","未來"))) | D39: =IF(A39="","",IF(A39='月度總覽'!$B$8,'月度總覽'!$B$9,0)) | E39: =IF(A39="","",SUMIFS('收支明細'!$E:$E,'收支明細'!$B:$B,"收入",'收支明細'!$A:$A,A39)) | F39: =IF(A39="","",SUMIFS('固定支出'!$C:$C,'固定支出'!$G:$G,"是",'固定支出'!$D:$D,A39)) | G39: =IF(A39="","",SUMIFS('收支明細'!$E:$E,'收支明細'!$B:$B,"支出",'收支明細'!$A:$A,A39)) | H39: =IF(OR(A39="",A39<'月度總覽'!$F$6),0,'月度總覽'!$F$13) -> 0.00 | I39: =IF(A39="","",D39+E39-G39) | J39: =IF(OR(A39="",A39<'月度總覽'!$F$6),"",'月度總覽'!$F$12-SUM($H$5:H39)+IF(AND('月度總覽'!$B$10="到帳日自動計入",'月度總覽'!$B$8>'月度總覽'!$B$7,'月度總覽'!$B$8<=A39),'月度總覽'!$B$9,0)+SUMIFS($E$5:E39,$A$5:A39,">"&'月度總覽'!$B$7)-SUMIFS($G$5:G39,$A$5:A39,">"&'月度總覽'!$B$7))
A40: =IF(36<='月度總覽'!$F$5,'月度總覽'!$B$5+36-1,"") | B40: =IF(A40="","",TEXT(A40,"aaa")) | C40: =IF(A40="","",IF(A40<'月度總覽'!$F$6,"已過",IF(A40='月度總覽'!$F$6,"基準日","未來"))) | D40: =IF(A40="","",IF(A40='月度總覽'!$B$8,'月度總覽'!$B$9,0)) | E40: =IF(A40="","",SUMIFS('收支明細'!$E:$E,'收支明細'!$B:$B,"收入",'收支明細'!$A:$A,A40)) | F40: =IF(A40="","",SUMIFS('固定支出'!$C:$C,'固定支出'!$G:$G,"是",'固定支出'!$D:$D,A40)) | G40: =IF(A40="","",SUMIFS('收支明細'!$E:$E,'收支明細'!$B:$B,"支出",'收支明細'!$A:$A,A40)) | H40: =IF(OR(A40="",A40<'月度總覽'!$F$6),0,'月度總覽'!$F$13) -> 0.00 | I40: =IF(A40="","",D40+E40-G40) | J40: =IF(OR(A40="",A40<'月度總覽'!$F$6),"",'月度總覽'!$F$12-SUM($H$5:H40)+IF(AND('月度總覽'!$B$10="到帳日自動計入",'月度總覽'!$B$8>'月度總覽'!$B$7,'月度總覽'!$B$8<=A40),'月度總覽'!$B$9,0)+SUMIFS($E$5:E40,$A$5:A40,">"&'月度總覽'!$B$7)-SUMIFS($G$5:G40,$A$5:A40,">"&'月度總覽'!$B$7))
A41: =IF(37<='月度總覽'!$F$5,'月度總覽'!$B$5+37-1,"") | B41: =IF(A41="","",TEXT(A41,"aaa")) | C41: =IF(A41="","",IF(A41<'月度總覽'!$F$6,"已過",IF(A41='月度總覽'!$F$6,"基準日","未來"))) | D41: =IF(A41="","",IF(A41='月度總覽'!$B$8,'月度總覽'!$B$9,0)) | E41: =IF(A41="","",SUMIFS('收支明細'!$E:$E,'收支明細'!$B:$B,"收入",'收支明細'!$A:$A,A41)) | F41: =IF(A41="","",SUMIFS('固定支出'!$C:$C,'固定支出'!$G:$G,"是",'固定支出'!$D:$D,A41)) | G41: =IF(A41="","",SUMIFS('收支明細'!$E:$E,'收支明細'!$B:$B,"支出",'收支明細'!$A:$A,A41)) | H41: =IF(OR(A41="",A41<'月度總覽'!$F$6),0,'月度總覽'!$F$13) -> 0.00 | I41: =IF(A41="","",D41+E41-G41) | J41: =IF(OR(A41="",A41<'月度總覽'!$F$6),"",'月度總覽'!$F$12-SUM($H$5:H41)+IF(AND('月度總覽'!$B$10="到帳日自動計入",'月度總覽'!$B$8>'月度總覽'!$B$7,'月度總覽'!$B$8<=A41),'月度總覽'!$B$9,0)+SUMIFS($E$5:E41,$A$5:A41,">"&'月度總覽'!$B$7)-SUMIFS($G$5:G41,$A$5:A41,">"&'月度總覽'!$B$7))
A42: =IF(38<='月度總覽'!$F$5,'月度總覽'!$B$5+38-1,"") | B42: =IF(A42="","",TEXT(A42,"aaa")) | C42: =IF(A42="","",IF(A42<'月度總覽'!$F$6,"已過",IF(A42='月度總覽'!$F$6,"基準日","未來"))) | D42: =IF(A42="","",IF(A42='月度總覽'!$B$8,'月度總覽'!$B$9,0)) | E42: =IF(A42="","",SUMIFS('收支明細'!$E:$E,'收支明細'!$B:$B,"收入",'收支明細'!$A:$A,A42)) | F42: =IF(A42="","",SUMIFS('固定支出'!$C:$C,'固定支出'!$G:$G,"是",'固定支出'!$D:$D,A42)) | G42: =IF(A42="","",SUMIFS('收支明細'!$E:$E,'收支明細'!$B:$B,"支出",'收支明細'!$A:$A,A42)) | H42: =IF(OR(A42="",A42<'月度總覽'!$F$6),0,'月度總覽'!$F$13) -> 0.00 | I42: =IF(A42="","",D42+E42-G42) | J42: =IF(OR(A42="",A42<'月度總覽'!$F$6),"",'月度總覽'!$F$12-SUM($H$5:H42)+IF(AND('月度總覽'!$B$10="到帳日自動計入",'月度總覽'!$B$8>'月度總覽'!$B$7,'月度總覽'!$B$8<=A42),'月度總覽'!$B$9,0)+SUMIFS($E$5:E42,$A$5:A42,">"&'月度總覽'!$B$7)-SUMIFS($G$5:G42,$A$5:A42,">"&'月度總覽'!$B$7))
A43: =IF(39<='月度總覽'!$F$5,'月度總覽'!$B$5+39-1,"") | B43: =IF(A43="","",TEXT(A43,"aaa")) | C43: =IF(A43="","",IF(A43<'月度總覽'!$F$6,"已過",IF(A43='月度總覽'!$F$6,"基準日","未來"))) | D43: =IF(A43="","",IF(A43='月度總覽'!$B$8,'月度總覽'!$B$9,0)) | E43: =IF(A43="","",SUMIFS('收支明細'!$E:$E,'收支明細'!$B:$B,"收入",'收支明細'!$A:$A,A43)) | F43: =IF(A43="","",SUMIFS('固定支出'!$C:$C,'固定支出'!$G:$G,"是",'固定支出'!$D:$D,A43)) | G43: =IF(A43="","",SUMIFS('收支明細'!$E:$E,'收支明細'!$B:$B,"支出",'收支明細'!$A:$A,A43)) | H43: =IF(OR(A43="",A43<'月度總覽'!$F$6),0,'月度總覽'!$F$13) -> 0.00 | I43: =IF(A43="","",D43+E43-G43) | J43: =IF(OR(A43="",A43<'月度總覽'!$F$6),"",'月度總覽'!$F$12-SUM($H$5:H43)+IF(AND('月度總覽'!$B$10="到帳日自動計入",'月度總覽'!$B$8>'月度總覽'!$B$7,'月度總覽'!$B$8<=A43),'月度總覽'!$B$9,0)+SUMIFS($E$5:E43,$A$5:A43,">"&'月度總覽'!$B$7)-SUMIFS($G$5:G43,$A$5:A43,">"&'月度總覽'!$B$7))
A44: =IF(40<='月度總覽'!$F$5,'月度總覽'!$B$5+40-1,"") | B44: =IF(A44="","",TEXT(A44,"aaa")) | C44: =IF(A44="","",IF(A44<'月度總覽'!$F$6,"已過",IF(A44='月度總覽'!$F$6,"基準日","未來"))) | D44: =IF(A44="","",IF(A44='月度總覽'!$B$8,'月度總覽'!$B$9,0)) | E44: =IF(A44="","",SUMIFS('收支明細'!$E:$E,'收支明細'!$B:$B,"收入",'收支明細'!$A:$A,A44)) | F44: =IF(A44="","",SUMIFS('固定支出'!$C:$C,'固定支出'!$G:$G,"是",'固定支出'!$D:$D,A44)) | G44: =IF(A44="","",SUMIFS('收支明細'!$E:$E,'收支明細'!$B:$B,"支出",'收支明細'!$A:$A,A44)) | H44: =IF(OR(A44="",A44<'月度總覽'!$F$6),0,'月度總覽'!$F$13) -> 0.00 | I44: =IF(A44="","",D44+E44-G44) | J44: =IF(OR(A44="",A44<'月度總覽'!$F$6),"",'月度總覽'!$F$12-SUM($H$5:H44)+IF(AND('月度總覽'!$B$10="到帳日自動計入",'月度總覽'!$B$8>'月度總覽'!$B$7,'月度總覽'!$B$8<=A44),'月度總覽'!$B$9,0)+SUMIFS($E$5:E44,$A$5:A44,">"&'月度總覽'!$B$7)-SUMIFS($G$5:G44,$A$5:A44,">"&'月度總覽'!$B$7))
A45: =IF(41<='月度總覽'!$F$5,'月度總覽'!$B$5+41-1,"") | B45: =IF(A45="","",TEXT(A45,"aaa")) | C45: =IF(A45="","",IF(A45<'月度總覽'!$F$6,"已過",IF(A45='月度總覽'!$F$6,"基準日","未來"))) | D45: =IF(A45="","",IF(A45='月度總覽'!$B$8,'月度總覽'!$B$9,0)) | E45: =IF(A45="","",SUMIFS('收支明細'!$E:$E,'收支明細'!$B:$B,"收入",'收支明細'!$A:$A,A45)) | F45: =IF(A45="","",SUMIFS('固定支出'!$C:$C,'固定支出'!$G:$G,"是",'固定支出'!$D:$D,A45)) | G45: =IF(A45="","",SUMIFS('收支明細'!$E:$E,'收支明細'!$B:$B,"支出",'收支明細'!$A:$A,A45)) | H45: =IF(OR(A45="",A45<'月度總覽'!$F$6),0,'月度總覽'!$F$13) -> 0.00 | I45: =IF(A45="","",D45+E45-G45) | J45: =IF(OR(A45="",A45<'月度總覽'!$F$6),"",'月度總覽'!$F$12-SUM($H$5:H45)+IF(AND('月度總覽'!$B$10="到帳日自動計入",'月度總覽'!$B$8>'月度總覽'!$B$7,'月度總覽'!$B$8<=A45),'月度總覽'!$B$9,0)+SUMIFS($E$5:E45,$A$5:A45,">"&'月度總覽'!$B$7)-SUMIFS($G$5:G45,$A$5:A45,">"&'月度總覽'!$B$7))
A46: =IF(42<='月度總覽'!$F$5,'月度總覽'!$B$5+42-1,"") | B46: =IF(A46="","",TEXT(A46,"aaa")) | C46: =IF(A46="","",IF(A46<'月度總覽'!$F$6,"已過",IF(A46='月度總覽'!$F$6,"基準日","未來"))) | D46: =IF(A46="","",IF(A46='月度總覽'!$B$8,'月度總覽'!$B$9,0)) | E46: =IF(A46="","",SUMIFS('收支明細'!$E:$E,'收支明細'!$B:$B,"收入",'收支明細'!$A:$A,A46)) | F46: =IF(A46="","",SUMIFS('固定支出'!$C:$C,'固定支出'!$G:$G,"是",'固定支出'!$D:$D,A46)) | G46: =IF(A46="","",SUMIFS('收支明細'!$E:$E,'收支明細'!$B:$B,"支出",'收支明細'!$A:$A,A46)) | H46: =IF(OR(A46="",A46<'月度總覽'!$F$6),0,'月度總覽'!$F$13) -> 0.00 | I46: =IF(A46="","",D46+E46-G46) | J46: =IF(OR(A46="",A46<'月度總覽'!$F$6),"",'月度總覽'!$F$12-SUM($H$5:H46)+IF(AND('月度總覽'!$B$10="到帳日自動計入",'月度總覽'!$B$8>'月度總覽'!$B$7,'月度總覽'!$B$8<=A46),'月度總覽'!$B$9,0)+SUMIFS($E$5:E46,$A$5:A46,">"&'月度總覽'!$B$7)-SUMIFS($G$5:G46,$A$5:A46,">"&'月度總覽'!$B$7))
A47: =IF(43<='月度總覽'!$F$5,'月度總覽'!$B$5+43-1,"") | B47: =IF(A47="","",TEXT(A47,"aaa")) | C47: =IF(A47="","",IF(A47<'月度總覽'!$F$6,"已過",IF(A47='月度總覽'!$F$6,"基準日","未來"))) | D47: =IF(A47="","",IF(A47='月度總覽'!$B$8,'月度總覽'!$B$9,0)) | E47: =IF(A47="","",SUMIFS('收支明細'!$E:$E,'收支明細'!$B:$B,"收入",'收支明細'!$A:$A,A47)) | F47: =IF(A47="","",SUMIFS('固定支出'!$C:$C,'固定支出'!$G:$G,"是",'固定支出'!$D:$D,A47)) | G47: =IF(A47="","",SUMIFS('收支明細'!$E:$E,'收支明細'!$B:$B,"支出",'收支明細'!$A:$A,A47)) | H47: =IF(OR(A47="",A47<'月度總覽'!$F$6),0,'月度總覽'!$F$13) -> 0.00 | I47: =IF(A47="","",D47+E47-G47) | J47: =IF(OR(A47="",A47<'月度總覽'!$F$6),"",'月度總覽'!$F$12-SUM($H$5:H47)+IF(AND('月度總覽'!$B$10="到帳日自動計入",'月度總覽'!$B$8>'月度總覽'!$B$7,'月度總覽'!$B$8<=A47),'月度總覽'!$B$9,0)+SUMIFS($E$5:E47,$A$5:A47,">"&'月度總覽'!$B$7)-SUMIFS($G$5:G47,$A$5:A47,">"&'月度總覽'!$B$7))
A48: =IF(44<='月度總覽'!$F$5,'月度總覽'!$B$5+44-1,"") | B48: =IF(A48="","",TEXT(A48,"aaa")) | C48: =IF(A48="","",IF(A48<'月度總覽'!$F$6,"已過",IF(A48='月度總覽'!$F$6,"基準日","未來"))) | D48: =IF(A48="","",IF(A48='月度總覽'!$B$8,'月度總覽'!$B$9,0)) | E48: =IF(A48="","",SUMIFS('收支明細'!$E:$E,'收支明細'!$B:$B,"收入",'收支明細'!$A:$A,A48)) | F48: =IF(A48="","",SUMIFS('固定支出'!$C:$C,'固定支出'!$G:$G,"是",'固定支出'!$D:$D,A48)) | G48: =IF(A48="","",SUMIFS('收支明細'!$E:$E,'收支明細'!$B:$B,"支出",'收支明細'!$A:$A,A48)) | H48: =IF(OR(A48="",A48<'月度總覽'!$F$6),0,'月度總覽'!$F$13) -> 0.00 | I48: =IF(A48="","",D48+E48-G48) | J48: =IF(OR(A48="",A48<'月度總覽'!$F$6),"",'月度總覽'!$F$12-SUM($H$5:H48)+IF(AND('月度總覽'!$B$10="到帳日自動計入",'月度總覽'!$B$8>'月度總覽'!$B$7,'月度總覽'!$B$8<=A48),'月度總覽'!$B$9,0)+SUMIFS($E$5:E48,$A$5:A48,">"&'月度總覽'!$B$7)-SUMIFS($G$5:G48,$A$5:A48,">"&'月度總覽'!$B$7))
A49: =IF(45<='月度總覽'!$F$5,'月度總覽'!$B$5+45-1,"") | B49: =IF(A49="","",TEXT(A49,"aaa")) | C49: =IF(A49="","",IF(A49<'月度總覽'!$F$6,"已過",IF(A49='月度總覽'!$F$6,"基準日","未來"))) | D49: =IF(A49="","",IF(A49='月度總覽'!$B$8,'月度總覽'!$B$9,0)) | E49: =IF(A49="","",SUMIFS('收支明細'!$E:$E,'收支明細'!$B:$B,"收入",'收支明細'!$A:$A,A49)) | F49: =IF(A49="","",SUMIFS('固定支出'!$C:$C,'固定支出'!$G:$G,"是",'固定支出'!$D:$D,A49)) | G49: =IF(A49="","",SUMIFS('收支明細'!$E:$E,'收支明細'!$B:$B,"支出",'收支明細'!$A:$A,A49)) | H49: =IF(OR(A49="",A49<'月度總覽'!$F$6),0,'月度總覽'!$F$13) -> 0.00 | I49: =IF(A49="","",D49+E49-G49) | J49: =IF(OR(A49="",A49<'月度總覽'!$F$6),"",'月度總覽'!$F$12-SUM($H$5:H49)+IF(AND('月度總覽'!$B$10="到帳日自動計入",'月度總覽'!$B$8>'月度總覽'!$B$7,'月度總覽'!$B$8<=A49),'月度總覽'!$B$9,0)+SUMIFS($E$5:E49,$A$5:A49,">"&'月度總覽'!$B$7)-SUMIFS($G$5:G49,$A$5:A49,">"&'月度總覽'!$B$7))
A50: =IF(46<='月度總覽'!$F$5,'月度總覽'!$B$5+46-1,"") | B50: =IF(A50="","",TEXT(A50,"aaa")) | C50: =IF(A50="","",IF(A50<'月度總覽'!$F$6,"已過",IF(A50='月度總覽'!$F$6,"基準日","未來"))) | D50: =IF(A50="","",IF(A50='月度總覽'!$B$8,'月度總覽'!$B$9,0)) | E50: =IF(A50="","",SUMIFS('收支明細'!$E:$E,'收支明細'!$B:$B,"收入",'收支明細'!$A:$A,A50)) | F50: =IF(A50="","",SUMIFS('固定支出'!$C:$C,'固定支出'!$G:$G,"是",'固定支出'!$D:$D,A50)) | G50: =IF(A50="","",SUMIFS('收支明細'!$E:$E,'收支明細'!$B:$B,"支出",'收支明細'!$A:$A,A50)) | H50: =IF(OR(A50="",A50<'月度總覽'!$F$6),0,'月度總覽'!$F$13) -> 0.00 | I50: =IF(A50="","",D50+E50-G50) | J50: =IF(OR(A50="",A50<'月度總覽'!$F$6),"",'月度總覽'!$F$12-SUM($H$5:H50)+IF(AND('月度總覽'!$B$10="到帳日自動計入",'月度總覽'!$B$8>'月度總覽'!$B$7,'月度總覽'!$B$8<=A50),'月度總覽'!$B$9,0)+SUMIFS($E$5:E50,$A$5:A50,">"&'月度總覽'!$B$7)-SUMIFS($G$5:G50,$A$5:A50,">"&'月度總覽'!$B$7))
A51: =IF(47<='月度總覽'!$F$5,'月度總覽'!$B$5+47-1,"") | B51: =IF(A51="","",TEXT(A51,"aaa")) | C51: =IF(A51="","",IF(A51<'月度總覽'!$F$6,"已過",IF(A51='月度總覽'!$F$6,"基準日","未來"))) | D51: =IF(A51="","",IF(A51='月度總覽'!$B$8,'月度總覽'!$B$9,0)) | E51: =IF(A51="","",SUMIFS('收支明細'!$E:$E,'收支明細'!$B:$B,"收入",'收支明細'!$A:$A,A51)) | F51: =IF(A51="","",SUMIFS('固定支出'!$C:$C,'固定支出'!$G:$G,"是",'固定支出'!$D:$D,A51)) | G51: =IF(A51="","",SUMIFS('收支明細'!$E:$E,'收支明細'!$B:$B,"支出",'收支明細'!$A:$A,A51)) | H51: =IF(OR(A51="",A51<'月度總覽'!$F$6),0,'月度總覽'!$F$13) -> 0.00 | I51: =IF(A51="","",D51+E51-G51) | J51: =IF(OR(A51="",A51<'月度總覽'!$F$6),"",'月度總覽'!$F$12-SUM($H$5:H51)+IF(AND('月度總覽'!$B$10="到帳日自動計入",'月度總覽'!$B$8>'月度總覽'!$B$7,'月度總覽'!$B$8<=A51),'月度總覽'!$B$9,0)+SUMIFS($E$5:E51,$A$5:A51,">"&'月度總覽'!$B$7)-SUMIFS($G$5:G51,$A$5:A51,">"&'月度總覽'!$B$7))
A52: =IF(48<='月度總覽'!$F$5,'月度總覽'!$B$5+48-1,"") | B52: =IF(A52="","",TEXT(A52,"aaa")) | C52: =IF(A52="","",IF(A52<'月度總覽'!$F$6,"已過",IF(A52='月度總覽'!$F$6,"基準日","未來"))) | D52: =IF(A52="","",IF(A52='月度總覽'!$B$8,'月度總覽'!$B$9,0)) | E52: =IF(A52="","",SUMIFS('收支明細'!$E:$E,'收支明細'!$B:$B,"收入",'收支明細'!$A:$A,A52)) | F52: =IF(A52="","",SUMIFS('固定支出'!$C:$C,'固定支出'!$G:$G,"是",'固定支出'!$D:$D,A52)) | G52: =IF(A52="","",SUMIFS('收支明細'!$E:$E,'收支明細'!$B:$B,"支出",'收支明細'!$A:$A,A52)) | H52: =IF(OR(A52="",A52<'月度總覽'!$F$6),0,'月度總覽'!$F$13) -> 0.00 | I52: =IF(A52="","",D52+E52-G52) | J52: =IF(OR(A52="",A52<'月度總覽'!$F$6),"",'月度總覽'!$F$12-SUM($H$5:H52)+IF(AND('月度總覽'!$B$10="到帳日自動計入",'月度總覽'!$B$8>'月度總覽'!$B$7,'月度總覽'!$B$8<=A52),'月度總覽'!$B$9,0)+SUMIFS($E$5:E52,$A$5:A52,">"&'月度總覽'!$B$7)-SUMIFS($G$5:G52,$A$5:A52,">"&'月度總覽'!$B$7))
A53: =IF(49<='月度總覽'!$F$5,'月度總覽'!$B$5+49-1,"") | B53: =IF(A53="","",TEXT(A53,"aaa")) | C53: =IF(A53="","",IF(A53<'月度總覽'!$F$6,"已過",IF(A53='月度總覽'!$F$6,"基準日","未來"))) | D53: =IF(A53="","",IF(A53='月度總覽'!$B$8,'月度總覽'!$B$9,0)) | E53: =IF(A53="","",SUMIFS('收支明細'!$E:$E,'收支明細'!$B:$B,"收入",'收支明細'!$A:$A,A53)) | F53: =IF(A53="","",SUMIFS('固定支出'!$C:$C,'固定支出'!$G:$G,"是",'固定支出'!$D:$D,A53)) | G53: =IF(A53="","",SUMIFS('收支明細'!$E:$E,'收支明細'!$B:$B,"支出",'收支明細'!$A:$A,A53)) | H53: =IF(OR(A53="",A53<'月度總覽'!$F$6),0,'月度總覽'!$F$13) -> 0.00 | I53: =IF(A53="","",D53+E53-G53) | J53: =IF(OR(A53="",A53<'月度總覽'!$F$6),"",'月度總覽'!$F$12-SUM($H$5:H53)+IF(AND('月度總覽'!$B$10="到帳日自動計入",'月度總覽'!$B$8>'月度總覽'!$B$7,'月度總覽'!$B$8<=A53),'月度總覽'!$B$9,0)+SUMIFS($E$5:E53,$A$5:A53,">"&'月度總覽'!$B$7)-SUMIFS($G$5:G53,$A$5:A53,">"&'月度總覽'!$B$7))
A54: =IF(50<='月度總覽'!$F$5,'月度總覽'!$B$5+50-1,"") | B54: =IF(A54="","",TEXT(A54,"aaa")) | C54: =IF(A54="","",IF(A54<'月度總覽'!$F$6,"已過",IF(A54='月度總覽'!$F$6,"基準日","未來"))) | D54: =IF(A54="","",IF(A54='月度總覽'!$B$8,'月度總覽'!$B$9,0)) | E54: =IF(A54="","",SUMIFS('收支明細'!$E:$E,'收支明細'!$B:$B,"收入",'收支明細'!$A:$A,A54)) | F54: =IF(A54="","",SUMIFS('固定支出'!$C:$C,'固定支出'!$G:$G,"是",'固定支出'!$D:$D,A54)) | G54: =IF(A54="","",SUMIFS('收支明細'!$E:$E,'收支明細'!$B:$B,"支出",'收支明細'!$A:$A,A54)) | H54: =IF(OR(A54="",A54<'月度總覽'!$F$6),0,'月度總覽'!$F$13) -> 0.00 | I54: =IF(A54="","",D54+E54-G54) | J54: =IF(OR(A54="",A54<'月度總覽'!$F$6),"",'月度總覽'!$F$12-SUM($H$5:H54)+IF(AND('月度總覽'!$B$10="到帳日自動計入",'月度總覽'!$B$8>'月度總覽'!$B$7,'月度總覽'!$B$8<=A54),'月度總覽'!$B$9,0)+SUMIFS($E$5:E54,$A$5:A54,">"&'月度總覽'!$B$7)-SUMIFS($G$5:G54,$A$5:A54,">"&'月度總覽'!$B$7))
A55: =IF(51<='月度總覽'!$F$5,'月度總覽'!$B$5+51-1,"") | B55: =IF(A55="","",TEXT(A55,"aaa")) | C55: =IF(A55="","",IF(A55<'月度總覽'!$F$6,"已過",IF(A55='月度總覽'!$F$6,"基準日","未來"))) | D55: =IF(A55="","",IF(A55='月度總覽'!$B$8,'月度總覽'!$B$9,0)) | E55: =IF(A55="","",SUMIFS('收支明細'!$E:$E,'收支明細'!$B:$B,"收入",'收支明細'!$A:$A,A55)) | F55: =IF(A55="","",SUMIFS('固定支出'!$C:$C,'固定支出'!$G:$G,"是",'固定支出'!$D:$D,A55)) | G55: =IF(A55="","",SUMIFS('收支明細'!$E:$E,'收支明細'!$B:$B,"支出",'收支明細'!$A:$A,A55)) | H55: =IF(OR(A55="",A55<'月度總覽'!$F$6),0,'月度總覽'!$F$13) -> 0.00 | I55: =IF(A55="","",D55+E55-G55) | J55: =IF(OR(A55="",A55<'月度總覽'!$F$6),"",'月度總覽'!$F$12-SUM($H$5:H55)+IF(AND('月度總覽'!$B$10="到帳日自動計入",'月度總覽'!$B$8>'月度總覽'!$B$7,'月度總覽'!$B$8<=A55),'月度總覽'!$B$9,0)+SUMIFS($E$5:E55,$A$5:A55,">"&'月度總覽'!$B$7)-SUMIFS($G$5:G55,$A$5:A55,">"&'月度總覽'!$B$7))
A56: =IF(52<='月度總覽'!$F$5,'月度總覽'!$B$5+52-1,"") | B56: =IF(A56="","",TEXT(A56,"aaa")) | C56: =IF(A56="","",IF(A56<'月度總覽'!$F$6,"已過",IF(A56='月度總覽'!$F$6,"基準日","未來"))) | D56: =IF(A56="","",IF(A56='月度總覽'!$B$8,'月度總覽'!$B$9,0)) | E56: =IF(A56="","",SUMIFS('收支明細'!$E:$E,'收支明細'!$B:$B,"收入",'收支明細'!$A:$A,A56)) | F56: =IF(A56="","",SUMIFS('固定支出'!$C:$C,'固定支出'!$G:$G,"是",'固定支出'!$D:$D,A56)) | G56: =IF(A56="","",SUMIFS('收支明細'!$E:$E,'收支明細'!$B:$B,"支出",'收支明細'!$A:$A,A56)) | H56: =IF(OR(A56="",A56<'月度總覽'!$F$6),0,'月度總覽'!$F$13) -> 0.00 | I56: =IF(A56="","",D56+E56-G56) | J56: =IF(OR(A56="",A56<'月度總覽'!$F$6),"",'月度總覽'!$F$12-SUM($H$5:H56)+IF(AND('月度總覽'!$B$10="到帳日自動計入",'月度總覽'!$B$8>'月度總覽'!$B$7,'月度總覽'!$B$8<=A56),'月度總覽'!$B$9,0)+SUMIFS($E$5:E56,$A$5:A56,">"&'月度總覽'!$B$7)-SUMIFS($G$5:G56,$A$5:A56,">"&'月度總覽'!$B$7))
A57: =IF(53<='月度總覽'!$F$5,'月度總覽'!$B$5+53-1,"") | B57: =IF(A57="","",TEXT(A57,"aaa")) | C57: =IF(A57="","",IF(A57<'月度總覽'!$F$6,"已過",IF(A57='月度總覽'!$F$6,"基準日","未來"))) | D57: =IF(A57="","",IF(A57='月度總覽'!$B$8,'月度總覽'!$B$9,0)) | E57: =IF(A57="","",SUMIFS('收支明細'!$E:$E,'收支明細'!$B:$B,"收入",'收支明細'!$A:$A,A57)) | F57: =IF(A57="","",SUMIFS('固定支出'!$C:$C,'固定支出'!$G:$G,"是",'固定支出'!$D:$D,A57)) | G57: =IF(A57="","",SUMIFS('收支明細'!$E:$E,'收支明細'!$B:$B,"支出",'收支明細'!$A:$A,A57)) | H57: =IF(OR(A57="",A57<'月度總覽'!$F$6),0,'月度總覽'!$F$13) -> 0.00 | I57: =IF(A57="","",D57+E57-G57) | J57: =IF(OR(A57="",A57<'月度總覽'!$F$6),"",'月度總覽'!$F$12-SUM($H$5:H57)+IF(AND('月度總覽'!$B$10="到帳日自動計入",'月度總覽'!$B$8>'月度總覽'!$B$7,'月度總覽'!$B$8<=A57),'月度總覽'!$B$9,0)+SUMIFS($E$5:E57,$A$5:A57,">"&'月度總覽'!$B$7)-SUMIFS($G$5:G57,$A$5:A57,">"&'月度總覽'!$B$7))
A58: =IF(54<='月度總覽'!$F$5,'月度總覽'!$B$5+54-1,"") | B58: =IF(A58="","",TEXT(A58,"aaa")) | C58: =IF(A58="","",IF(A58<'月度總覽'!$F$6,"已過",IF(A58='月度總覽'!$F$6,"基準日","未來"))) | D58: =IF(A58="","",IF(A58='月度總覽'!$B$8,'月度總覽'!$B$9,0)) | E58: =IF(A58="","",SUMIFS('收支明細'!$E:$E,'收支明細'!$B:$B,"收入",'收支明細'!$A:$A,A58)) | F58: =IF(A58="","",SUMIFS('固定支出'!$C:$C,'固定支出'!$G:$G,"是",'固定支出'!$D:$D,A58)) | G58: =IF(A58="","",SUMIFS('收支明細'!$E:$E,'收支明細'!$B:$B,"支出",'收支明細'!$A:$A,A58)) | H58: =IF(OR(A58="",A58<'月度總覽'!$F$6),0,'月度總覽'!$F$13) -> 0.00 | I58: =IF(A58="","",D58+E58-G58) | J58: =IF(OR(A58="",A58<'月度總覽'!$F$6),"",'月度總覽'!$F$12-SUM($H$5:H58)+IF(AND('月度總覽'!$B$10="到帳日自動計入",'月度總覽'!$B$8>'月度總覽'!$B$7,'月度總覽'!$B$8<=A58),'月度總覽'!$B$9,0)+SUMIFS($E$5:E58,$A$5:A58,">"&'月度總覽'!$B$7)-SUMIFS($G$5:G58,$A$5:A58,">"&'月度總覽'!$B$7))
A59: =IF(55<='月度總覽'!$F$5,'月度總覽'!$B$5+55-1,"") | B59: =IF(A59="","",TEXT(A59,"aaa")) | C59: =IF(A59="","",IF(A59<'月度總覽'!$F$6,"已過",IF(A59='月度總覽'!$F$6,"基準日","未來"))) | D59: =IF(A59="","",IF(A59='月度總覽'!$B$8,'月度總覽'!$B$9,0)) | E59: =IF(A59="","",SUMIFS('收支明細'!$E:$E,'收支明細'!$B:$B,"收入",'收支明細'!$A:$A,A59)) | F59: =IF(A59="","",SUMIFS('固定支出'!$C:$C,'固定支出'!$G:$G,"是",'固定支出'!$D:$D,A59)) | G59: =IF(A59="","",SUMIFS('收支明細'!$E:$E,'收支明細'!$B:$B,"支出",'收支明細'!$A:$A,A59)) | H59: =IF(OR(A59="",A59<'月度總覽'!$F$6),0,'月度總覽'!$F$13) -> 0.00 | I59: =IF(A59="","",D59+E59-G59) | J59: =IF(OR(A59="",A59<'月度總覽'!$F$6),"",'月度總覽'!$F$12-SUM($H$5:H59)+IF(AND('月度總覽'!$B$10="到帳日自動計入",'月度總覽'!$B$8>'月度總覽'!$B$7,'月度總覽'!$B$8<=A59),'月度總覽'!$B$9,0)+SUMIFS($E$5:E59,$A$5:A59,">"&'月度總覽'!$B$7)-SUMIFS($G$5:G59,$A$5:A59,">"&'月度總覽'!$B$7))
A60: =IF(56<='月度總覽'!$F$5,'月度總覽'!$B$5+56-1,"") | B60: =IF(A60="","",TEXT(A60,"aaa")) | C60: =IF(A60="","",IF(A60<'月度總覽'!$F$6,"已過",IF(A60='月度總覽'!$F$6,"基準日","未來"))) | D60: =IF(A60="","",IF(A60='月度總覽'!$B$8,'月度總覽'!$B$9,0)) | E60: =IF(A60="","",SUMIFS('收支明細'!$E:$E,'收支明細'!$B:$B,"收入",'收支明細'!$A:$A,A60)) | F60: =IF(A60="","",SUMIFS('固定支出'!$C:$C,'固定支出'!$G:$G,"是",'固定支出'!$D:$D,A60)) | G60: =IF(A60="","",SUMIFS('收支明細'!$E:$E,'收支明細'!$B:$B,"支出",'收支明細'!$A:$A,A60)) | H60: =IF(OR(A60="",A60<'月度總覽'!$F$6),0,'月度總覽'!$F$13) -> 0.00 | I60: =IF(A60="","",D60+E60-G60) | J60: =IF(OR(A60="",A60<'月度總覽'!$F$6),"",'月度總覽'!$F$12-SUM($H$5:H60)+IF(AND('月度總覽'!$B$10="到帳日自動計入",'月度總覽'!$B$8>'月度總覽'!$B$7,'月度總覽'!$B$8<=A60),'月度總覽'!$B$9,0)+SUMIFS($E$5:E60,$A$5:A60,">"&'月度總覽'!$B$7)-SUMIFS($G$5:G60,$A$5:A60,">"&'月度總覽'!$B$7))
A61: =IF(57<='月度總覽'!$F$5,'月度總覽'!$B$5+57-1,"") | B61: =IF(A61="","",TEXT(A61,"aaa")) | C61: =IF(A61="","",IF(A61<'月度總覽'!$F$6,"已過",IF(A61='月度總覽'!$F$6,"基準日","未來"))) | D61: =IF(A61="","",IF(A61='月度總覽'!$B$8,'月度總覽'!$B$9,0)) | E61: =IF(A61="","",SUMIFS('收支明細'!$E:$E,'收支明細'!$B:$B,"收入",'收支明細'!$A:$A,A61)) | F61: =IF(A61="","",SUMIFS('固定支出'!$C:$C,'固定支出'!$G:$G,"是",'固定支出'!$D:$D,A61)) | G61: =IF(A61="","",SUMIFS('收支明細'!$E:$E,'收支明細'!$B:$B,"支出",'收支明細'!$A:$A,A61)) | H61: =IF(OR(A61="",A61<'月度總覽'!$F$6),0,'月度總覽'!$F$13) -> 0.00 | I61: =IF(A61="","",D61+E61-G61) | J61: =IF(OR(A61="",A61<'月度總覽'!$F$6),"",'月度總覽'!$F$12-SUM($H$5:H61)+IF(AND('月度總覽'!$B$10="到帳日自動計入",'月度總覽'!$B$8>'月度總覽'!$B$7,'月度總覽'!$B$8<=A61),'月度總覽'!$B$9,0)+SUMIFS($E$5:E61,$A$5:A61,">"&'月度總覽'!$B$7)-SUMIFS($G$5:G61,$A$5:A61,">"&'月度總覽'!$B$7))
A62: =IF(58<='月度總覽'!$F$5,'月度總覽'!$B$5+58-1,"") | B62: =IF(A62="","",TEXT(A62,"aaa")) | C62: =IF(A62="","",IF(A62<'月度總覽'!$F$6,"已過",IF(A62='月度總覽'!$F$6,"基準日","未來"))) | D62: =IF(A62="","",IF(A62='月度總覽'!$B$8,'月度總覽'!$B$9,0)) | E62: =IF(A62="","",SUMIFS('收支明細'!$E:$E,'收支明細'!$B:$B,"收入",'收支明細'!$A:$A,A62)) | F62: =IF(A62="","",SUMIFS('固定支出'!$C:$C,'固定支出'!$G:$G,"是",'固定支出'!$D:$D,A62)) | G62: =IF(A62="","",SUMIFS('收支明細'!$E:$E,'收支明細'!$B:$B,"支出",'收支明細'!$A:$A,A62)) | H62: =IF(OR(A62="",A62<'月度總覽'!$F$6),0,'月度總覽'!$F$13) -> 0.00 | I62: =IF(A62="","",D62+E62-G62) | J62: =IF(OR(A62="",A62<'月度總覽'!$F$6),"",'月度總覽'!$F$12-SUM($H$5:H62)+IF(AND('月度總覽'!$B$10="到帳日自動計入",'月度總覽'!$B$8>'月度總覽'!$B$7,'月度總覽'!$B$8<=A62),'月度總覽'!$B$9,0)+SUMIFS($E$5:E62,$A$5:A62,">"&'月度總覽'!$B$7)-SUMIFS($G$5:G62,$A$5:A62,">"&'月度總覽'!$B$7))
A63: =IF(59<='月度總覽'!$F$5,'月度總覽'!$B$5+59-1,"") | B63: =IF(A63="","",TEXT(A63,"aaa")) | C63: =IF(A63="","",IF(A63<'月度總覽'!$F$6,"已過",IF(A63='月度總覽'!$F$6,"基準日","未來"))) | D63: =IF(A63="","",IF(A63='月度總覽'!$B$8,'月度總覽'!$B$9,0)) | E63: =IF(A63="","",SUMIFS('收支明細'!$E:$E,'收支明細'!$B:$B,"收入",'收支明細'!$A:$A,A63)) | F63: =IF(A63="","",SUMIFS('固定支出'!$C:$C,'固定支出'!$G:$G,"是",'固定支出'!$D:$D,A63)) | G63: =IF(A63="","",SUMIFS('收支明細'!$E:$E,'收支明細'!$B:$B,"支出",'收支明細'!$A:$A,A63)) | H63: =IF(OR(A63="",A63<'月度總覽'!$F$6),0,'月度總覽'!$F$13) -> 0.00 | I63: =IF(A63="","",D63+E63-G63) | J63: =IF(OR(A63="",A63<'月度總覽'!$F$6),"",'月度總覽'!$F$12-SUM($H$5:H63)+IF(AND('月度總覽'!$B$10="到帳日自動計入",'月度總覽'!$B$8>'月度總覽'!$B$7,'月度總覽'!$B$8<=A63),'月度總覽'!$B$9,0)+SUMIFS($E$5:E63,$A$5:A63,">"&'月度總覽'!$B$7)-SUMIFS($G$5:G63,$A$5:A63,">"&'月度總覽'!$B$7))
A64: =IF(60<='月度總覽'!$F$5,'月度總覽'!$B$5+60-1,"") | B64: =IF(A64="","",TEXT(A64,"aaa")) | C64: =IF(A64="","",IF(A64<'月度總覽'!$F$6,"已過",IF(A64='月度總覽'!$F$6,"基準日","未來"))) | D64: =IF(A64="","",IF(A64='月度總覽'!$B$8,'月度總覽'!$B$9,0)) | E64: =IF(A64="","",SUMIFS('收支明細'!$E:$E,'收支明細'!$B:$B,"收入",'收支明細'!$A:$A,A64)) | F64: =IF(A64="","",SUMIFS('固定支出'!$C:$C,'固定支出'!$G:$G,"是",'固定支出'!$D:$D,A64)) | G64: =IF(A64="","",SUMIFS('收支明細'!$E:$E,'收支明細'!$B:$B,"支出",'收支明細'!$A:$A,A64)) | H64: =IF(OR(A64="",A64<'月度總覽'!$F$6),0,'月度總覽'!$F$13) -> 0.00 | I64: =IF(A64="","",D64+E64-G64) | J64: =IF(OR(A64="",A64<'月度總覽'!$F$6),"",'月度總覽'!$F$12-SUM($H$5:H64)+IF(AND('月度總覽'!$B$10="到帳日自動計入",'月度總覽'!$B$8>'月度總覽'!$B$7,'月度總覽'!$B$8<=A64),'月度總覽'!$B$9,0)+SUMIFS($E$5:E64,$A$5:A64,">"&'月度總覽'!$B$7)-SUMIFS($G$5:G64,$A$5:A64,">"&'月度總覽'!$B$7))
A65: =IF(61<='月度總覽'!$F$5,'月度總覽'!$B$5+61-1,"") | B65: =IF(A65="","",TEXT(A65,"aaa")) | C65: =IF(A65="","",IF(A65<'月度總覽'!$F$6,"已過",IF(A65='月度總覽'!$F$6,"基準日","未來"))) | D65: =IF(A65="","",IF(A65='月度總覽'!$B$8,'月度總覽'!$B$9,0)) | E65: =IF(A65="","",SUMIFS('收支明細'!$E:$E,'收支明細'!$B:$B,"收入",'收支明細'!$A:$A,A65)) | F65: =IF(A65="","",SUMIFS('固定支出'!$C:$C,'固定支出'!$G:$G,"是",'固定支出'!$D:$D,A65)) | G65: =IF(A65="","",SUMIFS('收支明細'!$E:$E,'收支明細'!$B:$B,"支出",'收支明細'!$A:$A,A65)) | H65: =IF(OR(A65="",A65<'月度總覽'!$F$6),0,'月度總覽'!$F$13) -> 0.00 | I65: =IF(A65="","",D65+E65-G65) | J65: =IF(OR(A65="",A65<'月度總覽'!$F$6),"",'月度總覽'!$F$12-SUM($H$5:H65)+IF(AND('月度總覽'!$B$10="到帳日自動計入",'月度總覽'!$B$8>'月度總覽'!$B$7,'月度總覽'!$B$8<=A65),'月度總覽'!$B$9,0)+SUMIFS($E$5:E65,$A$5:A65,">"&'月度總覽'!$B$7)-SUMIFS($G$5:G65,$A$5:A65,">"&'月度總覽'!$B$7))
A66: =IF(62<='月度總覽'!$F$5,'月度總覽'!$B$5+62-1,"") | B66: =IF(A66="","",TEXT(A66,"aaa")) | C66: =IF(A66="","",IF(A66<'月度總覽'!$F$6,"已過",IF(A66='月度總覽'!$F$6,"基準日","未來"))) | D66: =IF(A66="","",IF(A66='月度總覽'!$B$8,'月度總覽'!$B$9,0)) | E66: =IF(A66="","",SUMIFS('收支明細'!$E:$E,'收支明細'!$B:$B,"收入",'收支明細'!$A:$A,A66)) | F66: =IF(A66="","",SUMIFS('固定支出'!$C:$C,'固定支出'!$G:$G,"是",'固定支出'!$D:$D,A66)) | G66: =IF(A66="","",SUMIFS('收支明細'!$E:$E,'收支明細'!$B:$B,"支出",'收支明細'!$A:$A,A66)) | H66: =IF(OR(A66="",A66<'月度總覽'!$F$6),0,'月度總覽'!$F$13) -> 0.00 | I66: =IF(A66="","",D66+E66-G66) | J66: =IF(OR(A66="",A66<'月度總覽'!$F$6),"",'月度總覽'!$F$12-SUM($H$5:H66)+IF(AND('月度總覽'!$B$10="到帳日自動計入",'月度總覽'!$B$8>'月度總覽'!$B$7,'月度總覽'!$B$8<=A66),'月度總覽'!$B$9,0)+SUMIFS($E$5:E66,$A$5:A66,">"&'月度總覽'!$B$7)-SUMIFS($G$5:G66,$A$5:A66,">"&'月度總覽'!$B$7))
A67: =IF(63<='月度總覽'!$F$5,'月度總覽'!$B$5+63-1,"") | B67: =IF(A67="","",TEXT(A67,"aaa")) | C67: =IF(A67="","",IF(A67<'月度總覽'!$F$6,"已過",IF(A67='月度總覽'!$F$6,"基準日","未來"))) | D67: =IF(A67="","",IF(A67='月度總覽'!$B$8,'月度總覽'!$B$9,0)) | E67: =IF(A67="","",SUMIFS('收支明細'!$E:$E,'收支明細'!$B:$B,"收入",'收支明細'!$A:$A,A67)) | F67: =IF(A67="","",SUMIFS('固定支出'!$C:$C,'固定支出'!$G:$G,"是",'固定支出'!$D:$D,A67)) | G67: =IF(A67="","",SUMIFS('收支明細'!$E:$E,'收支明細'!$B:$B,"支出",'收支明細'!$A:$A,A67)) | H67: =IF(OR(A67="",A67<'月度總覽'!$F$6),0,'月度總覽'!$F$13) -> 0.00 | I67: =IF(A67="","",D67+E67-G67) | J67: =IF(OR(A67="",A67<'月度總覽'!$F$6),"",'月度總覽'!$F$12-SUM($H$5:H67)+IF(AND('月度總覽'!$B$10="到帳日自動計入",'月度總覽'!$B$8>'月度總覽'!$B$7,'月度總覽'!$B$8<=A67),'月度總覽'!$B$9,0)+SUMIFS($E$5:E67,$A$5:A67,">"&'月度總覽'!$B$7)-SUMIFS($G$5:G67,$A$5:A67,">"&'月度總覽'!$B$7))
A68: =IF(64<='月度總覽'!$F$5,'月度總覽'!$B$5+64-1,"") | B68: =IF(A68="","",TEXT(A68,"aaa")) | C68: =IF(A68="","",IF(A68<'月度總覽'!$F$6,"已過",IF(A68='月度總覽'!$F$6,"基準日","未來"))) | D68: =IF(A68="","",IF(A68='月度總覽'!$B$8,'月度總覽'!$B$9,0)) | E68: =IF(A68="","",SUMIFS('收支明細'!$E:$E,'收支明細'!$B:$B,"收入",'收支明細'!$A:$A,A68)) | F68: =IF(A68="","",SUMIFS('固定支出'!$C:$C,'固定支出'!$G:$G,"是",'固定支出'!$D:$D,A68)) | G68: =IF(A68="","",SUMIFS('收支明細'!$E:$E,'收支明細'!$B:$B,"支出",'收支明細'!$A:$A,A68)) | H68: =IF(OR(A68="",A68<'月度總覽'!$F$6),0,'月度總覽'!$F$13) -> 0.00 | I68: =IF(A68="","",D68+E68-G68) | J68: =IF(OR(A68="",A68<'月度總覽'!$F$6),"",'月度總覽'!$F$12-SUM($H$5:H68)+IF(AND('月度總覽'!$B$10="到帳日自動計入",'月度總覽'!$B$8>'月度總覽'!$B$7,'月度總覽'!$B$8<=A68),'月度總覽'!$B$9,0)+SUMIFS($E$5:E68,$A$5:A68,">"&'月度總覽'!$B$7)-SUMIFS($G$5:G68,$A$5:A68,">"&'月度總覽'!$B$7))
A69: =IF(65<='月度總覽'!$F$5,'月度總覽'!$B$5+65-1,"") | B69: =IF(A69="","",TEXT(A69,"aaa")) | C69: =IF(A69="","",IF(A69<'月度總覽'!$F$6,"已過",IF(A69='月度總覽'!$F$6,"基準日","未來"))) | D69: =IF(A69="","",IF(A69='月度總覽'!$B$8,'月度總覽'!$B$9,0)) | E69: =IF(A69="","",SUMIFS('收支明細'!$E:$E,'收支明細'!$B:$B,"收入",'收支明細'!$A:$A,A69)) | F69: =IF(A69="","",SUMIFS('固定支出'!$C:$C,'固定支出'!$G:$G,"是",'固定支出'!$D:$D,A69)) | G69: =IF(A69="","",SUMIFS('收支明細'!$E:$E,'收支明細'!$B:$B,"支出",'收支明細'!$A:$A,A69)) | H69: =IF(OR(A69="",A69<'月度總覽'!$F$6),0,'月度總覽'!$F$13) -> 0.00 | I69: =IF(A69="","",D69+E69-G69) | J69: =IF(OR(A69="",A69<'月度總覽'!$F$6),"",'月度總覽'!$F$12-SUM($H$5:H69)+IF(AND('月度總覽'!$B$10="到帳日自動計入",'月度總覽'!$B$8>'月度總覽'!$B$7,'月度總覽'!$B$8<=A69),'月度總覽'!$B$9,0)+SUMIFS($E$5:E69,$A$5:A69,">"&'月度總覽'!$B$7)-SUMIFS($G$5:G69,$A$5:A69,">"&'月度總覽'!$B$7))
A70: =IF(66<='月度總覽'!$F$5,'月度總覽'!$B$5+66-1,"") | B70: =IF(A70="","",TEXT(A70,"aaa")) | C70: =IF(A70="","",IF(A70<'月度總覽'!$F$6,"已過",IF(A70='月度總覽'!$F$6,"基準日","未來"))) | D70: =IF(A70="","",IF(A70='月度總覽'!$B$8,'月度總覽'!$B$9,0)) | E70: =IF(A70="","",SUMIFS('收支明細'!$E:$E,'收支明細'!$B:$B,"收入",'收支明細'!$A:$A,A70)) | F70: =IF(A70="","",SUMIFS('固定支出'!$C:$C,'固定支出'!$G:$G,"是",'固定支出'!$D:$D,A70)) | G70: =IF(A70="","",SUMIFS('收支明細'!$E:$E,'收支明細'!$B:$B,"支出",'收支明細'!$A:$A,A70)) | H70: =IF(OR(A70="",A70<'月度總覽'!$F$6),0,'月度總覽'!$F$13) -> 0.00 | I70: =IF(A70="","",D70+E70-G70) | J70: =IF(OR(A70="",A70<'月度總覽'!$F$6),"",'月度總覽'!$F$12-SUM($H$5:H70)+IF(AND('月度總覽'!$B$10="到帳日自動計入",'月度總覽'!$B$8>'月度總覽'!$B$7,'月度總覽'!$B$8<=A70),'月度總覽'!$B$9,0)+SUMIFS($E$5:E70,$A$5:A70,">"&'月度總覽'!$B$7)-SUMIFS($G$5:G70,$A$5:A70,">"&'月度總覽'!$B$7))
A71: =IF(67<='月度總覽'!$F$5,'月度總覽'!$B$5+67-1,"") | B71: =IF(A71="","",TEXT(A71,"aaa")) | C71: =IF(A71="","",IF(A71<'月度總覽'!$F$6,"已過",IF(A71='月度總覽'!$F$6,"基準日","未來"))) | D71: =IF(A71="","",IF(A71='月度總覽'!$B$8,'月度總覽'!$B$9,0)) | E71: =IF(A71="","",SUMIFS('收支明細'!$E:$E,'收支明細'!$B:$B,"收入",'收支明細'!$A:$A,A71)) | F71: =IF(A71="","",SUMIFS('固定支出'!$C:$C,'固定支出'!$G:$G,"是",'固定支出'!$D:$D,A71)) | G71: =IF(A71="","",SUMIFS('收支明細'!$E:$E,'收支明細'!$B:$B,"支出",'收支明細'!$A:$A,A71)) | H71: =IF(OR(A71="",A71<'月度總覽'!$F$6),0,'月度總覽'!$F$13) -> 0.00 | I71: =IF(A71="","",D71+E71-G71) | J71: =IF(OR(A71="",A71<'月度總覽'!$F$6),"",'月度總覽'!$F$12-SUM($H$5:H71)+IF(AND('月度總覽'!$B$10="到帳日自動計入",'月度總覽'!$B$8>'月度總覽'!$B$7,'月度總覽'!$B$8<=A71),'月度總覽'!$B$9,0)+SUMIFS($E$5:E71,$A$5:A71,">"&'月度總覽'!$B$7)-SUMIFS($G$5:G71,$A$5:A71,">"&'月度總覽'!$B$7))
A72: =IF(68<='月度總覽'!$F$5,'月度總覽'!$B$5+68-1,"") | B72: =IF(A72="","",TEXT(A72,"aaa")) | C72: =IF(A72="","",IF(A72<'月度總覽'!$F$6,"已過",IF(A72='月度總覽'!$F$6,"基準日","未來"))) | D72: =IF(A72="","",IF(A72='月度總覽'!$B$8,'月度總覽'!$B$9,0)) | E72: =IF(A72="","",SUMIFS('收支明細'!$E:$E,'收支明細'!$B:$B,"收入",'收支明細'!$A:$A,A72)) | F72: =IF(A72="","",SUMIFS('固定支出'!$C:$C,'固定支出'!$G:$G,"是",'固定支出'!$D:$D,A72)) | G72: =IF(A72="","",SUMIFS('收支明細'!$E:$E,'收支明細'!$B:$B,"支出",'收支明細'!$A:$A,A72)) | H72: =IF(OR(A72="",A72<'月度總覽'!$F$6),0,'月度總覽'!$F$13) -> 0.00 | I72: =IF(A72="","",D72+E72-G72) | J72: =IF(OR(A72="",A72<'月度總覽'!$F$6),"",'月度總覽'!$F$12-SUM($H$5:H72)+IF(AND('月度總覽'!$B$10="到帳日自動計入",'月度總覽'!$B$8>'月度總覽'!$B$7,'月度總覽'!$B$8<=A72),'月度總覽'!$B$9,0)+SUMIFS($E$5:E72,$A$5:A72,">"&'月度總覽'!$B$7)-SUMIFS($G$5:G72,$A$5:A72,">"&'月度總覽'!$B$7))
A73: =IF(69<='月度總覽'!$F$5,'月度總覽'!$B$5+69-1,"") | B73: =IF(A73="","",TEXT(A73,"aaa")) | C73: =IF(A73="","",IF(A73<'月度總覽'!$F$6,"已過",IF(A73='月度總覽'!$F$6,"基準日","未來"))) | D73: =IF(A73="","",IF(A73='月度總覽'!$B$8,'月度總覽'!$B$9,0)) | E73: =IF(A73="","",SUMIFS('收支明細'!$E:$E,'收支明細'!$B:$B,"收入",'收支明細'!$A:$A,A73)) | F73: =IF(A73="","",SUMIFS('固定支出'!$C:$C,'固定支出'!$G:$G,"是",'固定支出'!$D:$D,A73)) | G73: =IF(A73="","",SUMIFS('收支明細'!$E:$E,'收支明細'!$B:$B,"支出",'收支明細'!$A:$A,A73)) | H73: =IF(OR(A73="",A73<'月度總覽'!$F$6),0,'月度總覽'!$F$13) -> 0.00 | I73: =IF(A73="","",D73+E73-G73) | J73: =IF(OR(A73="",A73<'月度總覽'!$F$6),"",'月度總覽'!$F$12-SUM($H$5:H73)+IF(AND('月度總覽'!$B$10="到帳日自動計入",'月度總覽'!$B$8>'月度總覽'!$B$7,'月度總覽'!$B$8<=A73),'月度總覽'!$B$9,0)+SUMIFS($E$5:E73,$A$5:A73,">"&'月度總覽'!$B$7)-SUMIFS($G$5:G73,$A$5:A73,">"&'月度總覽'!$B$7))
A74: =IF(70<='月度總覽'!$F$5,'月度總覽'!$B$5+70-1,"") | B74: =IF(A74="","",TEXT(A74,"aaa")) | C74: =IF(A74="","",IF(A74<'月度總覽'!$F$6,"已過",IF(A74='月度總覽'!$F$6,"基準日","未來"))) | D74: =IF(A74="","",IF(A74='月度總覽'!$B$8,'月度總覽'!$B$9,0)) | E74: =IF(A74="","",SUMIFS('收支明細'!$E:$E,'收支明細'!$B:$B,"收入",'收支明細'!$A:$A,A74)) | F74: =IF(A74="","",SUMIFS('固定支出'!$C:$C,'固定支出'!$G:$G,"是",'固定支出'!$D:$D,A74)) | G74: =IF(A74="","",SUMIFS('收支明細'!$E:$E,'收支明細'!$B:$B,"支出",'收支明細'!$A:$A,A74)) | H74: =IF(OR(A74="",A74<'月度總覽'!$F$6),0,'月度總覽'!$F$13) -> 0.00 | I74: =IF(A74="","",D74+E74-G74) | J74: =IF(OR(A74="",A74<'月度總覽'!$F$6),"",'月度總覽'!$F$12-SUM($H$5:H74)+IF(AND('月度總覽'!$B$10="到帳日自動計入",'月度總覽'!$B$8>'月度總覽'!$B$7,'月度總覽'!$B$8<=A74),'月度總覽'!$B$9,0)+SUMIFS($E$5:E74,$A$5:A74,">"&'月度總覽'!$B$7)-SUMIFS($G$5:G74,$A$5:A74,">"&'月度總覽'!$B$7))
A75: =IF(71<='月度總覽'!$F$5,'月度總覽'!$B$5+71-1,"") | B75: =IF(A75="","",TEXT(A75,"aaa")) | C75: =IF(A75="","",IF(A75<'月度總覽'!$F$6,"已過",IF(A75='月度總覽'!$F$6,"基準日","未來"))) | D75: =IF(A75="","",IF(A75='月度總覽'!$B$8,'月度總覽'!$B$9,0)) | E75: =IF(A75="","",SUMIFS('收支明細'!$E:$E,'收支明細'!$B:$B,"收入",'收支明細'!$A:$A,A75)) | F75: =IF(A75="","",SUMIFS('固定支出'!$C:$C,'固定支出'!$G:$G,"是",'固定支出'!$D:$D,A75)) | G75: =IF(A75="","",SUMIFS('收支明細'!$E:$E,'收支明細'!$B:$B,"支出",'收支明細'!$A:$A,A75)) | H75: =IF(OR(A75="",A75<'月度總覽'!$F$6),0,'月度總覽'!$F$13) -> 0.00 | I75: =IF(A75="","",D75+E75-G75) | J75: =IF(OR(A75="",A75<'月度總覽'!$F$6),"",'月度總覽'!$F$12-SUM($H$5:H75)+IF(AND('月度總覽'!$B$10="到帳日自動計入",'月度總覽'!$B$8>'月度總覽'!$B$7,'月度總覽'!$B$8<=A75),'月度總覽'!$B$9,0)+SUMIFS($E$5:E75,$A$5:A75,">"&'月度總覽'!$B$7)-SUMIFS($G$5:G75,$A$5:A75,">"&'月度總覽'!$B$7))
A76: =IF(72<='月度總覽'!$F$5,'月度總覽'!$B$5+72-1,"") | B76: =IF(A76="","",TEXT(A76,"aaa")) | C76: =IF(A76="","",IF(A76<'月度總覽'!$F$6,"已過",IF(A76='月度總覽'!$F$6,"基準日","未來"))) | D76: =IF(A76="","",IF(A76='月度總覽'!$B$8,'月度總覽'!$B$9,0)) | E76: =IF(A76="","",SUMIFS('收支明細'!$E:$E,'收支明細'!$B:$B,"收入",'收支明細'!$A:$A,A76)) | F76: =IF(A76="","",SUMIFS('固定支出'!$C:$C,'固定支出'!$G:$G,"是",'固定支出'!$D:$D,A76)) | G76: =IF(A76="","",SUMIFS('收支明細'!$E:$E,'收支明細'!$B:$B,"支出",'收支明細'!$A:$A,A76)) | H76: =IF(OR(A76="",A76<'月度總覽'!$F$6),0,'月度總覽'!$F$13) -> 0.00 | I76: =IF(A76="","",D76+E76-G76) | J76: =IF(OR(A76="",A76<'月度總覽'!$F$6),"",'月度總覽'!$F$12-SUM($H$5:H76)+IF(AND('月度總覽'!$B$10="到帳日自動計入",'月度總覽'!$B$8>'月度總覽'!$B$7,'月度總覽'!$B$8<=A76),'月度總覽'!$B$9,0)+SUMIFS($E$5:E76,$A$5:A76,">"&'月度總覽'!$B$7)-SUMIFS($G$5:G76,$A$5:A76,">"&'月度總覽'!$B$7))
A77: =IF(73<='月度總覽'!$F$5,'月度總覽'!$B$5+73-1,"") | B77: =IF(A77="","",TEXT(A77,"aaa")) | C77: =IF(A77="","",IF(A77<'月度總覽'!$F$6,"已過",IF(A77='月度總覽'!$F$6,"基準日","未來"))) | D77: =IF(A77="","",IF(A77='月度總覽'!$B$8,'月度總覽'!$B$9,0)) | E77: =IF(A77="","",SUMIFS('收支明細'!$E:$E,'收支明細'!$B:$B,"收入",'收支明細'!$A:$A,A77)) | F77: =IF(A77="","",SUMIFS('固定支出'!$C:$C,'固定支出'!$G:$G,"是",'固定支出'!$D:$D,A77)) | G77: =IF(A77="","",SUMIFS('收支明細'!$E:$E,'收支明細'!$B:$B,"支出",'收支明細'!$A:$A,A77)) | H77: =IF(OR(A77="",A77<'月度總覽'!$F$6),0,'月度總覽'!$F$13) -> 0.00 | I77: =IF(A77="","",D77+E77-G77) | J77: =IF(OR(A77="",A77<'月度總覽'!$F$6),"",'月度總覽'!$F$12-SUM($H$5:H77)+IF(AND('月度總覽'!$B$10="到帳日自動計入",'月度總覽'!$B$8>'月度總覽'!$B$7,'月度總覽'!$B$8<=A77),'月度總覽'!$B$9,0)+SUMIFS($E$5:E77,$A$5:A77,">"&'月度總覽'!$B$7)-SUMIFS($G$5:G77,$A$5:A77,">"&'月度總覽'!$B$7))
A78: =IF(74<='月度總覽'!$F$5,'月度總覽'!$B$5+74-1,"") | B78: =IF(A78="","",TEXT(A78,"aaa")) | C78: =IF(A78="","",IF(A78<'月度總覽'!$F$6,"已過",IF(A78='月度總覽'!$F$6,"基準日","未來"))) | D78: =IF(A78="","",IF(A78='月度總覽'!$B$8,'月度總覽'!$B$9,0)) | E78: =IF(A78="","",SUMIFS('收支明細'!$E:$E,'收支明細'!$B:$B,"收入",'收支明細'!$A:$A,A78)) | F78: =IF(A78="","",SUMIFS('固定支出'!$C:$C,'固定支出'!$G:$G,"是",'固定支出'!$D:$D,A78)) | G78: =IF(A78="","",SUMIFS('收支明細'!$E:$E,'收支明細'!$B:$B,"支出",'收支明細'!$A:$A,A78)) | H78: =IF(OR(A78="",A78<'月度總覽'!$F$6),0,'月度總覽'!$F$13) -> 0.00 | I78: =IF(A78="","",D78+E78-G78) | J78: =IF(OR(A78="",A78<'月度總覽'!$F$6),"",'月度總覽'!$F$12-SUM($H$5:H78)+IF(AND('月度總覽'!$B$10="到帳日自動計入",'月度總覽'!$B$8>'月度總覽'!$B$7,'月度總覽'!$B$8<=A78),'月度總覽'!$B$9,0)+SUMIFS($E$5:E78,$A$5:A78,">"&'月度總覽'!$B$7)-SUMIFS($G$5:G78,$A$5:A78,">"&'月度總覽'!$B$7))
A79: =IF(75<='月度總覽'!$F$5,'月度總覽'!$B$5+75-1,"") | B79: =IF(A79="","",TEXT(A79,"aaa")) | C79: =IF(A79="","",IF(A79<'月度總覽'!$F$6,"已過",IF(A79='月度總覽'!$F$6,"基準日","未來"))) | D79: =IF(A79="","",IF(A79='月度總覽'!$B$8,'月度總覽'!$B$9,0)) | E79: =IF(A79="","",SUMIFS('收支明細'!$E:$E,'收支明細'!$B:$B,"收入",'收支明細'!$A:$A,A79)) | F79: =IF(A79="","",SUMIFS('固定支出'!$C:$C,'固定支出'!$G:$G,"是",'固定支出'!$D:$D,A79)) | G79: =IF(A79="","",SUMIFS('收支明細'!$E:$E,'收支明細'!$B:$B,"支出",'收支明細'!$A:$A,A79)) | H79: =IF(OR(A79="",A79<'月度總覽'!$F$6),0,'月度總覽'!$F$13) -> 0.00 | I79: =IF(A79="","",D79+E79-G79) | J79: =IF(OR(A79="",A79<'月度總覽'!$F$6),"",'月度總覽'!$F$12-SUM($H$5:H79)+IF(AND('月度總覽'!$B$10="到帳日自動計入",'月度總覽'!$B$8>'月度總覽'!$B$7,'月度總覽'!$B$8<=A79),'月度總覽'!$B$9,0)+SUMIFS($E$5:E79,$A$5:A79,">"&'月度總覽'!$B$7)-SUMIFS($G$5:G79,$A$5:A79,">"&'月度總覽'!$B$7))
A80: =IF(76<='月度總覽'!$F$5,'月度總覽'!$B$5+76-1,"") | B80: =IF(A80="","",TEXT(A80,"aaa")) | C80: =IF(A80="","",IF(A80<'月度總覽'!$F$6,"已過",IF(A80='月度總覽'!$F$6,"基準日","未來"))) | D80: =IF(A80="","",IF(A80='月度總覽'!$B$8,'月度總覽'!$B$9,0)) | E80: =IF(A80="","",SUMIFS('收支明細'!$E:$E,'收支明細'!$B:$B,"收入",'收支明細'!$A:$A,A80)) | F80: =IF(A80="","",SUMIFS('固定支出'!$C:$C,'固定支出'!$G:$G,"是",'固定支出'!$D:$D,A80)) | G80: =IF(A80="","",SUMIFS('收支明細'!$E:$E,'收支明細'!$B:$B,"支出",'收支明細'!$A:$A,A80)) | H80: =IF(OR(A80="",A80<'月度總覽'!$F$6),0,'月度總覽'!$F$13) -> 0.00 | I80: =IF(A80="","",D80+E80-G80) | J80: =IF(OR(A80="",A80<'月度總覽'!$F$6),"",'月度總覽'!$F$12-SUM($H$5:H80)+IF(AND('月度總覽'!$B$10="到帳日自動計入",'月度總覽'!$B$8>'月度總覽'!$B$7,'月度總覽'!$B$8<=A80),'月度總覽'!$B$9,0)+SUMIFS($E$5:E80,$A$5:A80,">"&'月度總覽'!$B$7)-SUMIFS($G$5:G80,$A$5:A80,">"&'月度總覽'!$B$7))
A81: =IF(77<='月度總覽'!$F$5,'月度總覽'!$B$5+77-1,"") | B81: =IF(A81="","",TEXT(A81,"aaa")) | C81: =IF(A81="","",IF(A81<'月度總覽'!$F$6,"已過",IF(A81='月度總覽'!$F$6,"基準日","未來"))) | D81: =IF(A81="","",IF(A81='月度總覽'!$B$8,'月度總覽'!$B$9,0)) | E81: =IF(A81="","",SUMIFS('收支明細'!$E:$E,'收支明細'!$B:$B,"收入",'收支明細'!$A:$A,A81)) | F81: =IF(A81="","",SUMIFS('固定支出'!$C:$C,'固定支出'!$G:$G,"是",'固定支出'!$D:$D,A81)) | G81: =IF(A81="","",SUMIFS('收支明細'!$E:$E,'收支明細'!$B:$B,"支出",'收支明細'!$A:$A,A81)) | H81: =IF(OR(A81="",A81<'月度總覽'!$F$6),0,'月度總覽'!$F$13) -> 0.00 | I81: =IF(A81="","",D81+E81-G81) | J81: =IF(OR(A81="",A81<'月度總覽'!$F$6),"",'月度總覽'!$F$12-SUM($H$5:H81)+IF(AND('月度總覽'!$B$10="到帳日自動計入",'月度總覽'!$B$8>'月度總覽'!$B$7,'月度總覽'!$B$8<=A81),'月度總覽'!$B$9,0)+SUMIFS($E$5:E81,$A$5:A81,">"&'月度總覽'!$B$7)-SUMIFS($G$5:G81,$A$5:A81,">"&'月度總覽'!$B$7))
A82: =IF(78<='月度總覽'!$F$5,'月度總覽'!$B$5+78-1,"") | B82: =IF(A82="","",TEXT(A82,"aaa")) | C82: =IF(A82="","",IF(A82<'月度總覽'!$F$6,"已過",IF(A82='月度總覽'!$F$6,"基準日","未來"))) | D82: =IF(A82="","",IF(A82='月度總覽'!$B$8,'月度總覽'!$B$9,0)) | E82: =IF(A82="","",SUMIFS('收支明細'!$E:$E,'收支明細'!$B:$B,"收入",'收支明細'!$A:$A,A82)) | F82: =IF(A82="","",SUMIFS('固定支出'!$C:$C,'固定支出'!$G:$G,"是",'固定支出'!$D:$D,A82)) | G82: =IF(A82="","",SUMIFS('收支明細'!$E:$E,'收支明細'!$B:$B,"支出",'收支明細'!$A:$A,A82)) | H82: =IF(OR(A82="",A82<'月度總覽'!$F$6),0,'月度總覽'!$F$13) -> 0.00 | I82: =IF(A82="","",D82+E82-G82) | J82: =IF(OR(A82="",A82<'月度總覽'!$F$6),"",'月度總覽'!$F$12-SUM($H$5:H82)+IF(AND('月度總覽'!$B$10="到帳日自動計入",'月度總覽'!$B$8>'月度總覽'!$B$7,'月度總覽'!$B$8<=A82),'月度總覽'!$B$9,0)+SUMIFS($E$5:E82,$A$5:A82,">"&'月度總覽'!$B$7)-SUMIFS($G$5:G82,$A$5:A82,">"&'月度總覽'!$B$7))
A83: =IF(79<='月度總覽'!$F$5,'月度總覽'!$B$5+79-1,"") | B83: =IF(A83="","",TEXT(A83,"aaa")) | C83: =IF(A83="","",IF(A83<'月度總覽'!$F$6,"已過",IF(A83='月度總覽'!$F$6,"基準日","未來"))) | D83: =IF(A83="","",IF(A83='月度總覽'!$B$8,'月度總覽'!$B$9,0)) | E83: =IF(A83="","",SUMIFS('收支明細'!$E:$E,'收支明細'!$B:$B,"收入",'收支明細'!$A:$A,A83)) | F83: =IF(A83="","",SUMIFS('固定支出'!$C:$C,'固定支出'!$G:$G,"是",'固定支出'!$D:$D,A83)) | G83: =IF(A83="","",SUMIFS('收支明細'!$E:$E,'收支明細'!$B:$B,"支出",'收支明細'!$A:$A,A83)) | H83: =IF(OR(A83="",A83<'月度總覽'!$F$6),0,'月度總覽'!$F$13) -> 0.00 | I83: =IF(A83="","",D83+E83-G83) | J83: =IF(OR(A83="",A83<'月度總覽'!$F$6),"",'月度總覽'!$F$12-SUM($H$5:H83)+IF(AND('月度總覽'!$B$10="到帳日自動計入",'月度總覽'!$B$8>'月度總覽'!$B$7,'月度總覽'!$B$8<=A83),'月度總覽'!$B$9,0)+SUMIFS($E$5:E83,$A$5:A83,">"&'月度總覽'!$B$7)-SUMIFS($G$5:G83,$A$5:A83,">"&'月度總覽'!$B$7))
A84: =IF(80<='月度總覽'!$F$5,'月度總覽'!$B$5+80-1,"") | B84: =IF(A84="","",TEXT(A84,"aaa")) | C84: =IF(A84="","",IF(A84<'月度總覽'!$F$6,"已過",IF(A84='月度總覽'!$F$6,"基準日","未來"))) | D84: =IF(A84="","",IF(A84='月度總覽'!$B$8,'月度總覽'!$B$9,0)) | E84: =IF(A84="","",SUMIFS('收支明細'!$E:$E,'收支明細'!$B:$B,"收入",'收支明細'!$A:$A,A84)) | F84: =IF(A84="","",SUMIFS('固定支出'!$C:$C,'固定支出'!$G:$G,"是",'固定支出'!$D:$D,A84)) | G84: =IF(A84="","",SUMIFS('收支明細'!$E:$E,'收支明細'!$B:$B,"支出",'收支明細'!$A:$A,A84)) | H84: =IF(OR(A84="",A84<'月度總覽'!$F$6),0,'月度總覽'!$F$13) -> 0.00 | I84: =IF(A84="","",D84+E84-G84) | J84: =IF(OR(A84="",A84<'月度總覽'!$F$6),"",'月度總覽'!$F$12-SUM($H$5:H84)+IF(AND('月度總覽'!$B$10="到帳日自動計入",'月度總覽'!$B$8>'月度總覽'!$B$7,'月度總覽'!$B$8<=A84),'月度總覽'!$B$9,0)+SUMIFS($E$5:E84,$A$5:A84,">"&'月度總覽'!$B$7)-SUMIFS($G$5:G84,$A$5:A84,">"&'月度總覽'!$B$7))
A85: =IF(81<='月度總覽'!$F$5,'月度總覽'!$B$5+81-1,"") | B85: =IF(A85="","",TEXT(A85,"aaa")) | C85: =IF(A85="","",IF(A85<'月度總覽'!$F$6,"已過",IF(A85='月度總覽'!$F$6,"基準日","未來"))) | D85: =IF(A85="","",IF(A85='月度總覽'!$B$8,'月度總覽'!$B$9,0)) | E85: =IF(A85="","",SUMIFS('收支明細'!$E:$E,'收支明細'!$B:$B,"收入",'收支明細'!$A:$A,A85)) | F85: =IF(A85="","",SUMIFS('固定支出'!$C:$C,'固定支出'!$G:$G,"是",'固定支出'!$D:$D,A85)) | G85: =IF(A85="","",SUMIFS('收支明細'!$E:$E,'收支明細'!$B:$B,"支出",'收支明細'!$A:$A,A85)) | H85: =IF(OR(A85="",A85<'月度總覽'!$F$6),0,'月度總覽'!$F$13) -> 0.00 | I85: =IF(A85="","",D85+E85-G85) | J85: =IF(OR(A85="",A85<'月度總覽'!$F$6),"",'月度總覽'!$F$12-SUM($H$5:H85)+IF(AND('月度總覽'!$B$10="到帳日自動計入",'月度總覽'!$B$8>'月度總覽'!$B$7,'月度總覽'!$B$8<=A85),'月度總覽'!$B$9,0)+SUMIFS($E$5:E85,$A$5:A85,">"&'月度總覽'!$B$7)-SUMIFS($G$5:G85,$A$5:A85,">"&'月度總覽'!$B$7))
A86: =IF(82<='月度總覽'!$F$5,'月度總覽'!$B$5+82-1,"") | B86: =IF(A86="","",TEXT(A86,"aaa")) | C86: =IF(A86="","",IF(A86<'月度總覽'!$F$6,"已過",IF(A86='月度總覽'!$F$6,"基準日","未來"))) | D86: =IF(A86="","",IF(A86='月度總覽'!$B$8,'月度總覽'!$B$9,0)) | E86: =IF(A86="","",SUMIFS('收支明細'!$E:$E,'收支明細'!$B:$B,"收入",'收支明細'!$A:$A,A86)) | F86: =IF(A86="","",SUMIFS('固定支出'!$C:$C,'固定支出'!$G:$G,"是",'固定支出'!$D:$D,A86)) | G86: =IF(A86="","",SUMIFS('收支明細'!$E:$E,'收支明細'!$B:$B,"支出",'收支明細'!$A:$A,A86)) | H86: =IF(OR(A86="",A86<'月度總覽'!$F$6),0,'月度總覽'!$F$13) -> 0.00 | I86: =IF(A86="","",D86+E86-G86) | J86: =IF(OR(A86="",A86<'月度總覽'!$F$6),"",'月度總覽'!$F$12-SUM($H$5:H86)+IF(AND('月度總覽'!$B$10="到帳日自動計入",'月度總覽'!$B$8>'月度總覽'!$B$7,'月度總覽'!$B$8<=A86),'月度總覽'!$B$9,0)+SUMIFS($E$5:E86,$A$5:A86,">"&'月度總覽'!$B$7)-SUMIFS($G$5:G86,$A$5:A86,">"&'月度總覽'!$B$7))
A87: =IF(83<='月度總覽'!$F$5,'月度總覽'!$B$5+83-1,"") | B87: =IF(A87="","",TEXT(A87,"aaa")) | C87: =IF(A87="","",IF(A87<'月度總覽'!$F$6,"已過",IF(A87='月度總覽'!$F$6,"基準日","未來"))) | D87: =IF(A87="","",IF(A87='月度總覽'!$B$8,'月度總覽'!$B$9,0)) | E87: =IF(A87="","",SUMIFS('收支明細'!$E:$E,'收支明細'!$B:$B,"收入",'收支明細'!$A:$A,A87)) | F87: =IF(A87="","",SUMIFS('固定支出'!$C:$C,'固定支出'!$G:$G,"是",'固定支出'!$D:$D,A87)) | G87: =IF(A87="","",SUMIFS('收支明細'!$E:$E,'收支明細'!$B:$B,"支出",'收支明細'!$A:$A,A87)) | H87: =IF(OR(A87="",A87<'月度總覽'!$F$6),0,'月度總覽'!$F$13) -> 0.00 | I87: =IF(A87="","",D87+E87-G87) | J87: =IF(OR(A87="",A87<'月度總覽'!$F$6),"",'月度總覽'!$F$12-SUM($H$5:H87)+IF(AND('月度總覽'!$B$10="到帳日自動計入",'月度總覽'!$B$8>'月度總覽'!$B$7,'月度總覽'!$B$8<=A87),'月度總覽'!$B$9,0)+SUMIFS($E$5:E87,$A$5:A87,">"&'月度總覽'!$B$7)-SUMIFS($G$5:G87,$A$5:A87,">"&'月度總覽'!$B$7))
A88: =IF(84<='月度總覽'!$F$5,'月度總覽'!$B$5+84-1,"") | B88: =IF(A88="","",TEXT(A88,"aaa")) | C88: =IF(A88="","",IF(A88<'月度總覽'!$F$6,"已過",IF(A88='月度總覽'!$F$6,"基準日","未來"))) | D88: =IF(A88="","",IF(A88='月度總覽'!$B$8,'月度總覽'!$B$9,0)) | E88: =IF(A88="","",SUMIFS('收支明細'!$E:$E,'收支明細'!$B:$B,"收入",'收支明細'!$A:$A,A88)) | F88: =IF(A88="","",SUMIFS('固定支出'!$C:$C,'固定支出'!$G:$G,"是",'固定支出'!$D:$D,A88)) | G88: =IF(A88="","",SUMIFS('收支明細'!$E:$E,'收支明細'!$B:$B,"支出",'收支明細'!$A:$A,A88)) | H88: =IF(OR(A88="",A88<'月度總覽'!$F$6),0,'月度總覽'!$F$13) -> 0.00 | I88: =IF(A88="","",D88+E88-G88) | J88: =IF(OR(A88="",A88<'月度總覽'!$F$6),"",'月度總覽'!$F$12-SUM($H$5:H88)+IF(AND('月度總覽'!$B$10="到帳日自動計入",'月度總覽'!$B$8>'月度總覽'!$B$7,'月度總覽'!$B$8<=A88),'月度總覽'!$B$9,0)+SUMIFS($E$5:E88,$A$5:A88,">"&'月度總覽'!$B$7)-SUMIFS($G$5:G88,$A$5:A88,">"&'月度總覽'!$B$7))
A89: =IF(85<='月度總覽'!$F$5,'月度總覽'!$B$5+85-1,"") | B89: =IF(A89="","",TEXT(A89,"aaa")) | C89: =IF(A89="","",IF(A89<'月度總覽'!$F$6,"已過",IF(A89='月度總覽'!$F$6,"基準日","未來"))) | D89: =IF(A89="","",IF(A89='月度總覽'!$B$8,'月度總覽'!$B$9,0)) | E89: =IF(A89="","",SUMIFS('收支明細'!$E:$E,'收支明細'!$B:$B,"收入",'收支明細'!$A:$A,A89)) | F89: =IF(A89="","",SUMIFS('固定支出'!$C:$C,'固定支出'!$G:$G,"是",'固定支出'!$D:$D,A89)) | G89: =IF(A89="","",SUMIFS('收支明細'!$E:$E,'收支明細'!$B:$B,"支出",'收支明細'!$A:$A,A89)) | H89: =IF(OR(A89="",A89<'月度總覽'!$F$6),0,'月度總覽'!$F$13) -> 0.00 | I89: =IF(A89="","",D89+E89-G89) | J89: =IF(OR(A89="",A89<'月度總覽'!$F$6),"",'月度總覽'!$F$12-SUM($H$5:H89)+IF(AND('月度總覽'!$B$10="到帳日自動計入",'月度總覽'!$B$8>'月度總覽'!$B$7,'月度總覽'!$B$8<=A89),'月度總覽'!$B$9,0)+SUMIFS($E$5:E89,$A$5:A89,">"&'月度總覽'!$B$7)-SUMIFS($G$5:G89,$A$5:A89,">"&'月度總覽'!$B$7))
A90: =IF(86<='月度總覽'!$F$5,'月度總覽'!$B$5+86-1,"") | B90: =IF(A90="","",TEXT(A90,"aaa")) | C90: =IF(A90="","",IF(A90<'月度總覽'!$F$6,"已過",IF(A90='月度總覽'!$F$6,"基準日","未來"))) | D90: =IF(A90="","",IF(A90='月度總覽'!$B$8,'月度總覽'!$B$9,0)) | E90: =IF(A90="","",SUMIFS('收支明細'!$E:$E,'收支明細'!$B:$B,"收入",'收支明細'!$A:$A,A90)) | F90: =IF(A90="","",SUMIFS('固定支出'!$C:$C,'固定支出'!$G:$G,"是",'固定支出'!$D:$D,A90)) | G90: =IF(A90="","",SUMIFS('收支明細'!$E:$E,'收支明細'!$B:$B,"支出",'收支明細'!$A:$A,A90)) | H90: =IF(OR(A90="",A90<'月度總覽'!$F$6),0,'月度總覽'!$F$13) -> 0.00 | I90: =IF(A90="","",D90+E90-G90) | J90: =IF(OR(A90="",A90<'月度總覽'!$F$6),"",'月度總覽'!$F$12-SUM($H$5:H90)+IF(AND('月度總覽'!$B$10="到帳日自動計入",'月度總覽'!$B$8>'月度總覽'!$B$7,'月度總覽'!$B$8<=A90),'月度總覽'!$B$9,0)+SUMIFS($E$5:E90,$A$5:A90,">"&'月度總覽'!$B$7)-SUMIFS($G$5:G90,$A$5:A90,">"&'月度總覽'!$B$7))
A91: =IF(87<='月度總覽'!$F$5,'月度總覽'!$B$5+87-1,"") | B91: =IF(A91="","",TEXT(A91,"aaa")) | C91: =IF(A91="","",IF(A91<'月度總覽'!$F$6,"已過",IF(A91='月度總覽'!$F$6,"基準日","未來"))) | D91: =IF(A91="","",IF(A91='月度總覽'!$B$8,'月度總覽'!$B$9,0)) | E91: =IF(A91="","",SUMIFS('收支明細'!$E:$E,'收支明細'!$B:$B,"收入",'收支明細'!$A:$A,A91)) | F91: =IF(A91="","",SUMIFS('固定支出'!$C:$C,'固定支出'!$G:$G,"是",'固定支出'!$D:$D,A91)) | G91: =IF(A91="","",SUMIFS('收支明細'!$E:$E,'收支明細'!$B:$B,"支出",'收支明細'!$A:$A,A91)) | H91: =IF(OR(A91="",A91<'月度總覽'!$F$6),0,'月度總覽'!$F$13) -> 0.00 | I91: =IF(A91="","",D91+E91-G91) | J91: =IF(OR(A91="",A91<'月度總覽'!$F$6),"",'月度總覽'!$F$12-SUM($H$5:H91)+IF(AND('月度總覽'!$B$10="到帳日自動計入",'月度總覽'!$B$8>'月度總覽'!$B$7,'月度總覽'!$B$8<=A91),'月度總覽'!$B$9,0)+SUMIFS($E$5:E91,$A$5:A91,">"&'月度總覽'!$B$7)-SUMIFS($G$5:G91,$A$5:A91,">"&'月度總覽'!$B$7))
A92: =IF(88<='月度總覽'!$F$5,'月度總覽'!$B$5+88-1,"") | B92: =IF(A92="","",TEXT(A92,"aaa")) | C92: =IF(A92="","",IF(A92<'月度總覽'!$F$6,"已過",IF(A92='月度總覽'!$F$6,"基準日","未來"))) | D92: =IF(A92="","",IF(A92='月度總覽'!$B$8,'月度總覽'!$B$9,0)) | E92: =IF(A92="","",SUMIFS('收支明細'!$E:$E,'收支明細'!$B:$B,"收入",'收支明細'!$A:$A,A92)) | F92: =IF(A92="","",SUMIFS('固定支出'!$C:$C,'固定支出'!$G:$G,"是",'固定支出'!$D:$D,A92)) | G92: =IF(A92="","",SUMIFS('收支明細'!$E:$E,'收支明細'!$B:$B,"支出",'收支明細'!$A:$A,A92)) | H92: =IF(OR(A92="",A92<'月度總覽'!$F$6),0,'月度總覽'!$F$13) -> 0.00 | I92: =IF(A92="","",D92+E92-G92) | J92: =IF(OR(A92="",A92<'月度總覽'!$F$6),"",'月度總覽'!$F$12-SUM($H$5:H92)+IF(AND('月度總覽'!$B$10="到帳日自動計入",'月度總覽'!$B$8>'月度總覽'!$B$7,'月度總覽'!$B$8<=A92),'月度總覽'!$B$9,0)+SUMIFS($E$5:E92,$A$5:A92,">"&'月度總覽'!$B$7)-SUMIFS($G$5:G92,$A$5:A92,">"&'月度總覽'!$B$7))
A93: =IF(89<='月度總覽'!$F$5,'月度總覽'!$B$5+89-1,"") | B93: =IF(A93="","",TEXT(A93,"aaa")) | C93: =IF(A93="","",IF(A93<'月度總覽'!$F$6,"已過",IF(A93='月度總覽'!$F$6,"基準日","未來"))) | D93: =IF(A93="","",IF(A93='月度總覽'!$B$8,'月度總覽'!$B$9,0)) | E93: =IF(A93="","",SUMIFS('收支明細'!$E:$E,'收支明細'!$B:$B,"收入",'收支明細'!$A:$A,A93)) | F93: =IF(A93="","",SUMIFS('固定支出'!$C:$C,'固定支出'!$G:$G,"是",'固定支出'!$D:$D,A93)) | G93: =IF(A93="","",SUMIFS('收支明細'!$E:$E,'收支明細'!$B:$B,"支出",'收支明細'!$A:$A,A93)) | H93: =IF(OR(A93="",A93<'月度總覽'!$F$6),0,'月度總覽'!$F$13) -> 0.00 | I93: =IF(A93="","",D93+E93-G93) | J93: =IF(OR(A93="",A93<'月度總覽'!$F$6),"",'月度總覽'!$F$12-SUM($H$5:H93)+IF(AND('月度總覽'!$B$10="到帳日自動計入",'月度總覽'!$B$8>'月度總覽'!$B$7,'月度總覽'!$B$8<=A93),'月度總覽'!$B$9,0)+SUMIFS($E$5:E93,$A$5:A93,">"&'月度總覽'!$B$7)-SUMIFS($G$5:G93,$A$5:A93,">"&'月度總覽'!$B$7))
A94: =IF(90<='月度總覽'!$F$5,'月度總覽'!$B$5+90-1,"") | B94: =IF(A94="","",TEXT(A94,"aaa")) | C94: =IF(A94="","",IF(A94<'月度總覽'!$F$6,"已過",IF(A94='月度總覽'!$F$6,"基準日","未來"))) | D94: =IF(A94="","",IF(A94='月度總覽'!$B$8,'月度總覽'!$B$9,0)) | E94: =IF(A94="","",SUMIFS('收支明細'!$E:$E,'收支明細'!$B:$B,"收入",'收支明細'!$A:$A,A94)) | F94: =IF(A94="","",SUMIFS('固定支出'!$C:$C,'固定支出'!$G:$G,"是",'固定支出'!$D:$D,A94)) | G94: =IF(A94="","",SUMIFS('收支明細'!$E:$E,'收支明細'!$B:$B,"支出",'收支明細'!$A:$A,A94)) | H94: =IF(OR(A94="",A94<'月度總覽'!$F$6),0,'月度總覽'!$F$13) -> 0.00 | I94: =IF(A94="","",D94+E94-G94) | J94: =IF(OR(A94="",A94<'月度總覽'!$F$6),"",'月度總覽'!$F$12-SUM($H$5:H94)+IF(AND('月度總覽'!$B$10="到帳日自動計入",'月度總覽'!$B$8>'月度總覽'!$B$7,'月度總覽'!$B$8<=A94),'月度總覽'!$B$9,0)+SUMIFS($E$5:E94,$A$5:A94,">"&'月度總覽'!$B$7)-SUMIFS($G$5:G94,$A$5:A94,">"&'月度總覽'!$B$7))
A95: =IF(91<='月度總覽'!$F$5,'月度總覽'!$B$5+91-1,"") | B95: =IF(A95="","",TEXT(A95,"aaa")) | C95: =IF(A95="","",IF(A95<'月度總覽'!$F$6,"已過",IF(A95='月度總覽'!$F$6,"基準日","未來"))) | D95: =IF(A95="","",IF(A95='月度總覽'!$B$8,'月度總覽'!$B$9,0)) | E95: =IF(A95="","",SUMIFS('收支明細'!$E:$E,'收支明細'!$B:$B,"收入",'收支明細'!$A:$A,A95)) | F95: =IF(A95="","",SUMIFS('固定支出'!$C:$C,'固定支出'!$G:$G,"是",'固定支出'!$D:$D,A95)) | G95: =IF(A95="","",SUMIFS('收支明細'!$E:$E,'收支明細'!$B:$B,"支出",'收支明細'!$A:$A,A95)) | H95: =IF(OR(A95="",A95<'月度總覽'!$F$6),0,'月度總覽'!$F$13) -> 0.00 | I95: =IF(A95="","",D95+E95-G95) | J95: =IF(OR(A95="",A95<'月度總覽'!$F$6),"",'月度總覽'!$F$12-SUM($H$5:H95)+IF(AND('月度總覽'!$B$10="到帳日自動計入",'月度總覽'!$B$8>'月度總覽'!$B$7,'月度總覽'!$B$8<=A95),'月度總覽'!$B$9,0)+SUMIFS($E$5:E95,$A$5:A95,">"&'月度總覽'!$B$7)-SUMIFS($G$5:G95,$A$5:A95,">"&'月度總覽'!$B$7))
A96: =IF(92<='月度總覽'!$F$5,'月度總覽'!$B$5+92-1,"") | B96: =IF(A96="","",TEXT(A96,"aaa")) | C96: =IF(A96="","",IF(A96<'月度總覽'!$F$6,"已過",IF(A96='月度總覽'!$F$6,"基準日","未來"))) | D96: =IF(A96="","",IF(A96='月度總覽'!$B$8,'月度總覽'!$B$9,0)) | E96: =IF(A96="","",SUMIFS('收支明細'!$E:$E,'收支明細'!$B:$B,"收入",'收支明細'!$A:$A,A96)) | F96: =IF(A96="","",SUMIFS('固定支出'!$C:$C,'固定支出'!$G:$G,"是",'固定支出'!$D:$D,A96)) | G96: =IF(A96="","",SUMIFS('收支明細'!$E:$E,'收支明細'!$B:$B,"支出",'收支明細'!$A:$A,A96)) | H96: =IF(OR(A96="",A96<'月度總覽'!$F$6),0,'月度總覽'!$F$13) -> 0.00 | I96: =IF(A96="","",D96+E96-G96) | J96: =IF(OR(A96="",A96<'月度總覽'!$F$6),"",'月度總覽'!$F$12-SUM($H$5:H96)+IF(AND('月度總覽'!$B$10="到帳日自動計入",'月度總覽'!$B$8>'月度總覽'!$B$7,'月度總覽'!$B$8<=A96),'月度總覽'!$B$9,0)+SUMIFS($E$5:E96,$A$5:A96,">"&'月度總覽'!$B$7)-SUMIFS($G$5:G96,$A$5:A96,">"&'月度總覽'!$B$7))
A97: =IF(93<='月度總覽'!$F$5,'月度總覽'!$B$5+93-1,"") | B97: =IF(A97="","",TEXT(A97,"aaa")) | C97: =IF(A97="","",IF(A97<'月度總覽'!$F$6,"已過",IF(A97='月度總覽'!$F$6,"基準日","未來"))) | D97: =IF(A97="","",IF(A97='月度總覽'!$B$8,'月度總覽'!$B$9,0)) | E97: =IF(A97="","",SUMIFS('收支明細'!$E:$E,'收支明細'!$B:$B,"收入",'收支明細'!$A:$A,A97)) | F97: =IF(A97="","",SUMIFS('固定支出'!$C:$C,'固定支出'!$G:$G,"是",'固定支出'!$D:$D,A97)) | G97: =IF(A97="","",SUMIFS('收支明細'!$E:$E,'收支明細'!$B:$B,"支出",'收支明細'!$A:$A,A97)) | H97: =IF(OR(A97="",A97<'月度總覽'!$F$6),0,'月度總覽'!$F$13) -> 0.00 | I97: =IF(A97="","",D97+E97-G97) | J97: =IF(OR(A97="",A97<'月度總覽'!$F$6),"",'月度總覽'!$F$12-SUM($H$5:H97)+IF(AND('月度總覽'!$B$10="到帳日自動計入",'月度總覽'!$B$8>'月度總覽'!$B$7,'月度總覽'!$B$8<=A97),'月度總覽'!$B$9,0)+SUMIFS($E$5:E97,$A$5:A97,">"&'月度總覽'!$B$7)-SUMIFS($G$5:G97,$A$5:A97,">"&'月度總覽'!$B$7))
A98: =IF(94<='月度總覽'!$F$5,'月度總覽'!$B$5+94-1,"") | B98: =IF(A98="","",TEXT(A98,"aaa")) | C98: =IF(A98="","",IF(A98<'月度總覽'!$F$6,"已過",IF(A98='月度總覽'!$F$6,"基準日","未來"))) | D98: =IF(A98="","",IF(A98='月度總覽'!$B$8,'月度總覽'!$B$9,0)) | E98: =IF(A98="","",SUMIFS('收支明細'!$E:$E,'收支明細'!$B:$B,"收入",'收支明細'!$A:$A,A98)) | F98: =IF(A98="","",SUMIFS('固定支出'!$C:$C,'固定支出'!$G:$G,"是",'固定支出'!$D:$D,A98)) | G98: =IF(A98="","",SUMIFS('收支明細'!$E:$E,'收支明細'!$B:$B,"支出",'收支明細'!$A:$A,A98)) | H98: =IF(OR(A98="",A98<'月度總覽'!$F$6),0,'月度總覽'!$F$13) -> 0.00 | I98: =IF(A98="","",D98+E98-G98) | J98: =IF(OR(A98="",A98<'月度總覽'!$F$6),"",'月度總覽'!$F$12-SUM($H$5:H98)+IF(AND('月度總覽'!$B$10="到帳日自動計入",'月度總覽'!$B$8>'月度總覽'!$B$7,'月度總覽'!$B$8<=A98),'月度總覽'!$B$9,0)+SUMIFS($E$5:E98,$A$5:A98,">"&'月度總覽'!$B$7)-SUMIFS($G$5:G98,$A$5:A98,">"&'月度總覽'!$B$7))
A99: =IF(95<='月度總覽'!$F$5,'月度總覽'!$B$5+95-1,"") | B99: =IF(A99="","",TEXT(A99,"aaa")) | C99: =IF(A99="","",IF(A99<'月度總覽'!$F$6,"已過",IF(A99='月度總覽'!$F$6,"基準日","未來"))) | D99: =IF(A99="","",IF(A99='月度總覽'!$B$8,'月度總覽'!$B$9,0)) | E99: =IF(A99="","",SUMIFS('收支明細'!$E:$E,'收支明細'!$B:$B,"收入",'收支明細'!$A:$A,A99)) | F99: =IF(A99="","",SUMIFS('固定支出'!$C:$C,'固定支出'!$G:$G,"是",'固定支出'!$D:$D,A99)) | G99: =IF(A99="","",SUMIFS('收支明細'!$E:$E,'收支明細'!$B:$B,"支出",'收支明細'!$A:$A,A99)) | H99: =IF(OR(A99="",A99<'月度總覽'!$F$6),0,'月度總覽'!$F$13) -> 0.00 | I99: =IF(A99="","",D99+E99-G99) | J99: =IF(OR(A99="",A99<'月度總覽'!$F$6),"",'月度總覽'!$F$12-SUM($H$5:H99)+IF(AND('月度總覽'!$B$10="到帳日自動計入",'月度總覽'!$B$8>'月度總覽'!$B$7,'月度總覽'!$B$8<=A99),'月度總覽'!$B$9,0)+SUMIFS($E$5:E99,$A$5:A99,">"&'月度總覽'!$B$7)-SUMIFS($G$5:G99,$A$5:A99,">"&'月度總覽'!$B$7))
A100: =IF(96<='月度總覽'!$F$5,'月度總覽'!$B$5+96-1,"") | B100: =IF(A100="","",TEXT(A100,"aaa")) | C100: =IF(A100="","",IF(A100<'月度總覽'!$F$6,"已過",IF(A100='月度總覽'!$F$6,"基準日","未來"))) | D100: =IF(A100="","",IF(A100='月度總覽'!$B$8,'月度總覽'!$B$9,0)) | E100: =IF(A100="","",SUMIFS('收支明細'!$E:$E,'收支明細'!$B:$B,"收入",'收支明細'!$A:$A,A100)) | F100: =IF(A100="","",SUMIFS('固定支出'!$C:$C,'固定支出'!$G:$G,"是",'固定支出'!$D:$D,A100)) | G100: =IF(A100="","",SUMIFS('收支明細'!$E:$E,'收支明細'!$B:$B,"支出",'收支明細'!$A:$A,A100)) | H100: =IF(OR(A100="",A100<'月度總覽'!$F$6),0,'月度總覽'!$F$13) -> 0.00 | I100: =IF(A100="","",D100+E100-G100) | J100: =IF(OR(A100="",A100<'月度總覽'!$F$6),"",'月度總覽'!$F$12-SUM($H$5:H100)+IF(AND('月度總覽'!$B$10="到帳日自動計入",'月度總覽'!$B$8>'月度總覽'!$B$7,'月度總覽'!$B$8<=A100),'月度總覽'!$B$9,0)+SUMIFS($E$5:E100,$A$5:A100,">"&'月度總覽'!$B$7)-SUMIFS($G$5:G100,$A$5:A100,">"&'月度總覽'!$B$7))
A101: =IF(97<='月度總覽'!$F$5,'月度總覽'!$B$5+97-1,"") | B101: =IF(A101="","",TEXT(A101,"aaa")) | C101: =IF(A101="","",IF(A101<'月度總覽'!$F$6,"已過",IF(A101='月度總覽'!$F$6,"基準日","未來"))) | D101: =IF(A101="","",IF(A101='月度總覽'!$B$8,'月度總覽'!$B$9,0)) | E101: =IF(A101="","",SUMIFS('收支明細'!$E:$E,'收支明細'!$B:$B,"收入",'收支明細'!$A:$A,A101)) | F101: =IF(A101="","",SUMIFS('固定支出'!$C:$C,'固定支出'!$G:$G,"是",'固定支出'!$D:$D,A101)) | G101: =IF(A101="","",SUMIFS('收支明細'!$E:$E,'收支明細'!$B:$B,"支出",'收支明細'!$A:$A,A101)) | H101: =IF(OR(A101="",A101<'月度總覽'!$F$6),0,'月度總覽'!$F$13) -> 0.00 | I101: =IF(A101="","",D101+E101-G101) | J101: =IF(OR(A101="",A101<'月度總覽'!$F$6),"",'月度總覽'!$F$12-SUM($H$5:H101)+IF(AND('月度總覽'!$B$10="到帳日自動計入",'月度總覽'!$B$8>'月度總覽'!$B$7,'月度總覽'!$B$8<=A101),'月度總覽'!$B$9,0)+SUMIFS($E$5:E101,$A$5:A101,">"&'月度總覽'!$B$7)-SUMIFS($G$5:G101,$A$5:A101,">"&'月度總覽'!$B$7))
...

Sheet 選單設定
A1: 支出／收入類別 | B1: 付款方式 | C1: 收支類型 | D1: 是／否 | E1: 薪資計入方式 | G1: 說明
A2: 餐飲 | B2: 現金 | C2: 支出 | D2: 是 | E2: 到帳日自動計入 | G2: 可直接修改／新增 A、B 欄選項；下拉選單預留至第 50 列。
A3: 交通 | B3: 信用卡 | C3: 收入 | D3: 否 | E3: 全期預先計入 | G3: 請勿刪除 C～E 欄的核心選項，否則公式判斷可能失效。
A4: 居住 | B4: 扣帳卡 | E4: 不計入
A5: 水電煤 | B5: 轉數快
A6: 通訊 | B6: 銀行轉帳
A7: 保險 | B7: 八達通
A8: 醫療 | B8: 自動轉帳
A9: 日用品 | B9: 其他
A10: 娛樂
A11: 教育
A12: 投資
A13: 薪資
A14: 其他收入
A15: 其他支出

Sheet 使用說明
A1: 使用說明｜閉環操作流程
A3: 1. 設定結果邊界 | B3: 在「月度總覽」黃色欄位輸入自訂開始日、結束日、配額基準日、發薪日、薪資、薪資計入方式與期初餘額。
A4: 2. 預留固定支出 | B4: 在「固定支出」輸入本期完整扣款日期、金額；未付款且啟用的項目會先由可變動資金扣除。
A5: 3. 記錄真實收支 | B5: 在「收支明細」逐筆登記。金額一律輸入正數，以『類型』區分收入或支出。薪資由總覽自動處理，勿重複登記。
A6: 4. 完成固定支出閉環 | B6: 付款後：①在收支明細登記該筆支出；②在固定支出把『已付款』改為『是』。如此預留會被實支替代，不會重複扣款。
A7: 5. 查看動態配額 | B7: 總覽以（期初餘額＋已計入薪資＋其他收入－實際支出－未付固定支出）÷剩餘天數，重算每天平均配額。負數時配額顯示 0。
A8: 6. 查看順向結果 | B8: 「每日順向結果」逐日展示薪資、收入、固定支出、實支、建議支出與預測可變資金；基準日以黃色標示。
A9: 7. 自訂下拉選單 | B9: 在「選單設定」修改類別和付款方式。新增項目可放到第 50 列；核心的收支類型、是／否、薪資計入方式不要刪除。
A12: 公式口徑 | B12: 動態每日配額會依配額基準日變化。若選『到帳日自動計入』，未到帳薪資不會提前提高當日配額；到帳後會自動納入。
